{
    "Adelia Mar\u00eda": "AMA", 
    "Almafuerte": "ALE", 
    "Arias": "ARI", 
    "Arroyito": "AYO", 
    "Ballesteros": "BES", 
    "Bell Ville": "BVL", 
    "Bengolea": "BEA", 
    "Caleta C\u00f3rdoba": "CLC", 
    "Canals": "CNL", 
    "Carnerillo": "CAO", 
    "Colazo": "CZO", 
    "Colonia Caroya": "CRY", 
    "Cruz Alta": "CAZ", 
    "Cruz del Eje": "CDE", 
    "C\u00f3rdoba": "COR", 
    "Frontera": "FRT", 
    "General Cabrera": "GCA", 
    "General Deheza": "GDL", 
    "Ju\u00e1rez Celman": "JUA", 
    "La Calera": "LCR", 
    "La Cumbre": "LCM", 
    "La Falda": "LFL", 
    "Las Higueras": "LHG", 
    "Monte Cristo": "MCR", 
    "Monte Ma\u00edz": "MML", 
    "Pozo del Molle": "PDM", 
    "R\u00edo Cuarto": "RCU", 
    "R\u00edo Tercero": "RTO", 
    "San Antonio de Arredondo": "SAA", 
    "San Francisco": "SFO", 
    "Ticino": "TIC", 
    "Villa Dolores": "VDR", 
    "Villa Mar\u00eda": "VMR", 
    "Villa Nueva": "VNA", 
    "Villa del Totoral": "VTT"
}