{
    "Abbott Park": "ABJ", 
    "Abingdon": "ABG", 
    "Addison": "UAP", 
    "Albany": "AJB", 
    "Albers": "LXR", 
    "Albion": "AOB", 
    "Aledo": "AD5", 
    "Alexander": "ZXA", 
    "Alexis": "LEV", 
    "Algonquin": "AGQ", 
    "Alorton": "ZON", 
    "Alpha": "AJQ", 
    "Alsip": "UBC", 
    "Altamont": "AZN", 
    "Alton": "ALN", 
    "Amboy": "AMY", 
    "Andalusia": "USQ", 
    "Anna": "YRU", 
    "Antioch": "TIH", 
    "Arcola": "AKV", 
    "Arenzville": "ARS", 
    "Argenta": "7AR", 
    "Argo": "XBB", 
    "Arlington": "RLG", 
    "Arlington Heights": "JLH", 
    "Aroma Park": "6AP", 
    "Arthur": "AXH", 
    "Ashkum": "ASM", 
    "Ashland": "7AI", 
    "Ashley": "AS4", 
    "Ashmore": "AOH", 
    "Ashton": "AYA", 
    "Assumption": "AMP", 
    "Astoria": "AT4", 
    "Athens": "AZH", 
    "Atkinson": "3AI", 
    "Atlanta": "AZI", 
    "Attica": "AJZ", 
    "Atwood": "6AT", 
    "Auburn": "UUN", 
    "Augusta": "7AU", 
    "Aurora": "AUZ", 
    "Ava": "A2V", 
    "Avery Hill": "AYB", 
    "Avon": "VON", 
    "Baldwin": "ZBN", 
    "Bannockburn": "BNN", 
    "Barrington": "BRQ", 
    "Barry": "YRB", 
    "Bartlett": "BIJ", 
    "Bartonville": "BCJ", 
    "Batavia": "BTA", 
    "Beardstown": "BEA", 
    "Beaverville": "VL8", 
    "Beckemeyer": "BEC", 
    "Bedford Park": "BDP", 
    "Beecher": "DBC", 
    "Belleville": "BLV", 
    "Bellevue": "6BV", 
    "Bellwood": "UFA", 
    "Beloit": "BT7", 
    "Belvidere": "BVJ", 
    "Bement": "7BM", 
    "Bensenville": "BNV", 
    "Benson": "QES", 
    "Benton": "BTQ", 
    "Berkeley": "BKK", 
    "Berwyn": "BWY", 
    "Bethalto": "6BT", 
    "Bethany": "BTX", 
    "Binghampton": "BH2", 
    "Bismarck": "2BS", 
    "Blandinsville": "4BV", 
    "Bloomingdale": "OMI", 
    "Bloomington": "B2L", 
    "Bloomington-Normal Apt": "BMI", 
    "Blue Island": "BCU", 
    "Blue Mound": "5BM", 
    "Bluffs": "BJU", 
    "Bolingbrook": "BNK", 
    "Bourbonnais": "USA", 
    "Braceville": "9BR", 
    "Bradford": "BDF", 
    "Bradley": "BYL", 
    "Braidwood": "6BW", 
    "Breese": "BXD", 
    "Bridgeport": "4BP", 
    "Bridgeview": "QVW", 
    "Brighton": "GXO", 
    "Brimfield": "BRM", 
    "Bristol": "QBX", 
    "Broadview": "BRJ", 
    "Brookfield": "IBF", 
    "Brookport": "8BR", 
    "Brownstown": "5BR", 
    "Buda": "ILU", 
    "Buffalo Grove": "BGO", 
    "Bull Valley": "BU3", 
    "Bunker Hill": "ZBA", 
    "Burbank": "BUK", 
    "Bureau": "2BU", 
    "Burlington": "BL7", 
    "Burnham": "4BH", 
    "Burr Ridge": "BGB", 
    "Bushnell": "BGC", 
    "Butler": "QUR", 
    "Byron": "XYB", 
    "Byron Hills Estates": "7BY", 
    "Cache": "ZVC", 
    "Cahokia": "CK5", 
    "Cairo": "CIR", 
    "Calhoun": "C6H", 
    "Calumet City": "CAY", 
    "Calumet Park": "CUP", 
    "Cambria": "9CM", 
    "Cambridge": "2CB", 
    "Camp Point": "3CP", 
    "Campbell Hill": "JPI", 
    "Canton": "CTJ", 
    "Capron": "CJ7", 
    "Carbon Cliff": "4CC", 
    "Carbondale": "MDH", 
    "Carlinville": "VCN", 
    "Carlock": "C9A", 
    "Carlyle": "IYC", 
    "Carmi": "AMI", 
    "Carol Stream": "ACE", 
    "Carpentersville": "CRV", 
    "Carrier Mills": "CM9", 
    "Carrollton": "C5K", 
    "Carterville": "4CV", 
    "Carthage": "RTG", 
    "Cary": "AYI", 
    "Casey": "AJY", 
    "Caseyville": "CV9", 
    "Catlin": "8CL", 
    "Cave-in-Rock": "VRK", 
    "Centerville": "C2T", 
    "Central City": "6CN", 
    "Centralia": "ENL", 
    "Centreville": "CIU", 
    "Cerro Gordo": "CGJ", 
    "Champaign": "CMI", 
    "Chandlerville": "5CH", 
    "Channahon": "CHH", 
    "Charleston": "ILC", 
    "Chatham": "CZ7", 
    "Chatsworth": "TS4", 
    "Chebanse": "CSB", 
    "Chenoa": "JHA", 
    "Chester": "CSI", 
    "Chicago": "CHI", 
    "Chicago Heights": "CGH", 
    "Chicago Ridge": "CRG", 
    "Chillicothe": "CH2", 
    "Chrisman": "HJ9", 
    "Christopher": "IPH", 
    "Cicero": "XDN", 
    "Cisne": "9CS", 
    "Cissna Park": "8CS", 
    "Clare": "QAI", 
    "Claremont": "9CL", 
    "Clarendon Hill": "CH4", 
    "Clarendon Hills": "VNH", 
    "Clark": "6CK", 
    "Clay City": "5CT", 
    "Clayton": "CKY", 
    "Clearing": "CIZ", 
    "Cleveland": "CL5", 
    "Clinton": "ICC", 
    "Coal City": "COY", 
    "Coal Valley": "ZCV", 
    "Cobden": "5CD", 
    "Coffeen": "C5N", 
    "Colchester": "DGI", 
    "Coles": "7CO", 
    "Colfax": "9CF", 
    "Collinsville": "YCL", 
    "Colona": "2CO", 
    "Columbia": "CL6", 
    "Columbus": "CB9", 
    "Compton": "KVO", 
    "Cordova": "ODV", 
    "Cortland": "TND", 
    "Cottage Grove": "QGV", 
    "Cottage Hills": "2CH", 
    "Coulterville": "CV6", 
    "Country Club Hills": "CU9", 
    "Country Side": "CBJ", 
    "Countryside": "3CS", 
    "Creal Springs": "EFP", 
    "Crest Hill": "CH5", 
    "Crestwood": "CWB", 
    "Crete": "CQQ", 
    "Creve Coeur": "CXD", 
    "Crossville": "7CR", 
    "Crystal Lake": "CTD", 
    "Crystal Lawns": "2CL", 
    "Cuba": "JCB", 
    "Cumberland": "4CM", 
    "Dakota": "DKO", 
    "Dallas City": "DCX", 
    "Danvers": "YYS", 
    "Danville": "DVI", 
    "Darien": "DII", 
    "Davis Junction": "DJ9", 
    "De Kalb": "DEK", 
    "De Soto": "OT4", 
    "DeKalb": "DCB", 
    "Decatur": "DEC", 
    "Deer Grove": "DGR", 
    "Deer Park": "FJY", 
    "Deerfield": "DRD", 
    "Delavan": "D9E", 
    "Depue": "DE5", 
    "Des Plaines": "DES", 
    "Detroit": "DTT", 
    "Dewitt": "DEZ", 
    "Diamond Lake": "2DK", 
    "Dieterich": "D2H", 
    "Divernon": "4DV", 
    "Dixmoor": "DMR", 
    "Dixon": "DXN", 
    "Dolton": "DQN", 
    "Dongola": "DNG", 
    "Donovan": "ZDV", 
    "Douglas": "3DL", 
    "Dover": "DER", 
    "Downers Grove": "UFO", 
    "Downs": "4DO", 
    "Du Quoin": "DUU", 
    "Dundee": "DYI", 
    "Dunlap": "DJR", 
    "Dupo": "DUP", 
    "Duquoin": "DUQ", 
    "Durand": "DDI", 
    "Dwight": "DWI", 
    "Earlville": "8EV", 
    "East Alton": "EOL", 
    "East Carondelet": "TCD", 
    "East Clinton": "ECL", 
    "East Dubuque": "EQE", 
    "East Dundee": "9ED", 
    "East Hazel Crest": "EHC", 
    "East Moline": "EMN", 
    "East Peoria": "EPO", 
    "East Saint Louis": "ESL", 
    "Edwards": "EZD", 
    "Edwardsville": "EWV", 
    "Effingham": "EFI", 
    "El Paso": "EPX", 
    "Elburn": "EB2", 
    "Elco": "EQO", 
    "Eldorado": "ED2", 
    "Elgin": "EGN", 
    "Elizabeth": "6EZ", 
    "Elk Grove": "EGI", 
    "Elk Grove Village": "EVI", 
    "Elkhart": "EKJ", 
    "Elkville": "5EK", 
    "Ellsworth": "EXH", 
    "Elmhurst": "ELR", 
    "Elmwood": "EXW", 
    "Elmwood Park": "EMW", 
    "Elsah": "4EL", 
    "Elwood": "EWI", 
    "Emden": "EJX", 
    "Energy": "ERG", 
    "Enfield": "6EF", 
    "Equality": "QIY", 
    "Erie": "ERZ", 
    "Eureka": "2EK", 
    "Evanston": "EVD", 
    "Evansville": "EVN", 
    "Evergreen Park": "EP3", 
    "Fairbury": "FB2", 
    "Fairfield": "FAD", 
    "Fairmont": "3FR", 
    "Fairmont City": "QFY", 
    "Fairmont, Will": "FMW", 
    "Fairmount": "FIO", 
    "Fairview": "4FV", 
    "Fairview Heights": "FIH", 
    "Fargo": "ZFG", 
    "Farina": "5FI", 
    "Farmer City": "5FC", 
    "Farmingdale": "8FD", 
    "Farmington": "7FG", 
    "Fayette": "3FY", 
    "Fayetteville": "FYZ", 
    "Findlay": "FY8", 
    "Fisher": "FHR", 
    "Fithian": "IHN", 
    "Flanagan": "FG7", 
    "Flat Rock": "LTK", 
    "Flora": "AEA", 
    "Flossmoor": "FSX", 
    "Ford Heights": "FHG", 
    "Forest City": "FCC", 
    "Forest Park": "FPA", 
    "Forest View": "FTW", 
    "Forrest": "FZE", 
    "Forreston": "FRB", 
    "Forsyth": "FYH", 
    "Fort Sheridan": "FSN", 
    "Fox River Grove": "FOZ", 
    "Frankfort": "FJK", 
    "Franklin Park": "FLI", 
    "Freeburg": "FBU", 
    "Freeport": "FEP", 
    "Fulton": "ZFL", 
    "Galena": "VKA", 
    "Galesburg": "GBG", 
    "Galva": "GVS", 
    "Gardner": "GJD", 
    "Geneseo": "ZGZ", 
    "Geneva": "GNI", 
    "Genoa": "GOI", 
    "Georgetown, Fayette": "GWN", 
    "Germantown": "GEA", 
    "Gibson City": "GBC", 
    "Gilberts": "YOG", 
    "Gilman": "GMA", 
    "Gilson": "GIK", 
    "Girard": "IAR", 
    "Glen Ellyn": "GEL", 
    "Glen View": "GVX", 
    "Glencoe": "EOE", 
    "Glendale Heights": "G2H", 
    "Glendale Hghts": "GHI", 
    "Glenview": "NBU", 
    "Glenwood": "OOG", 
    "Godfrey": "GDF", 
    "Golden": "JGN", 
    "Golf": "QGL", 
    "Goodfield": "GF4", 
    "Grand Ridge": "GYJ", 
    "Granite City": "GZI", 
    "Grant Park": "GRK", 
    "Granville": "ZVG", 
    "Grayslake": "GYL", 
    "Grayville": "GQE", 
    "Great Lakes": "GRL", 
    "Green Oaks": "ZDM", 
    "Greenup": "GU2", 
    "Greenview": "USI", 
    "Greenville": "GRE", 
    "Greenwood": "GW5", 
    "Gridley": "XFY", 
    "Griggsville": "GGF", 
    "Gurnee": "GUR", 
    "Hamel": "QHL", 
    "Hamilton": "ZDX", 
    "Hammond": "HM9", 
    "Hampshire": "HPS", 
    "Hanover": "QHV", 
    "Hanover Park": "HPK", 
    "Harmon": "HVO", 
    "Harrisburg": "HSB", 
    "Harristown": "HS9", 
    "Hartford": "HFI", 
    "Harvard": "HRU", 
    "Harvey": "HRY", 
    "Harwood Heights": "HHT", 
    "Havana": "HVV", 
    "Hazel Crest": "HZS", 
    "Hebron": "HEO", 
    "Hennepin": "NNP", 
    "Henry": "HYY", 
    "Herod": "KHD", 
    "Herrin": "HER", 
    "Heyworth": "HYW", 
    "Hickory Hills, Cook": "HHC", 
    "Highland": "HGL", 
    "Highland Park": "HIA", 
    "Highwood": "HH8", 
    "Hillsdale": "KHI", 
    "Hillside": "UJO", 
    "Hinsdale": "HSA", 
    "Hodgkins": "HOK", 
    "Hoffman Estates": "HME", 
    "Holcomb": "HCM", 
    "Holland, Effingham": "HL6", 
    "Homer Glen": "AOF", 
    "Homewood": "HMW", 
    "Hoopeston": "HUP", 
    "Hudson": "HCU", 
    "Huntley": "HTQ", 
    "Illinois City": "ZFT", 
    "Illiopolis": "ILP", 
    "Ingleside": "IEG", 
    "Inverness": "IVS", 
    "Itasca": "ITS", 
    "Ivesdale": "VDE", 
    "Jacksonville": "IJX", 
    "Janesville": "JVV", 
    "Jerseyville": "YJY", 
    "Johnsburg": "JBG", 
    "Johnsonville": "JS8", 
    "Joliet": "JOT", 
    "Joppa": "JPA", 
    "Joslin": "JSL", 
    "Justice": "JTC", 
    "Kaneville": "KAV", 
    "Kankakee": "IKK", 
    "Keithsburg": "KBU", 
    "Kenilworth": "KWR", 
    "Kenney": "KQS", 
    "Kewanee": "KEW", 
    "Keyesport": "KEE", 
    "Kildeer": "KD4", 
    "Kinsman": "KFM", 
    "Kirkland": "KKZ", 
    "Knoxville": "OXV", 
    "La Fayette": "VLF", 
    "La Grange": "LAI", 
    "La Grange Highlands": "LGZ", 
    "La Grange Park": "LPG", 
    "La Harpe": "LA4", 
    "La Salle": "UJY", 
    "Lacon": "L7A", 
    "Ladd": "LDD", 
    "Lafayette": "LA7", 
    "Lake Barrington": "KBO", 
    "Lake Bluff": "LBC", 
    "Lake Forest": "LFR", 
    "Lake In The Hills": "LKI", 
    "Lake Villa": "VIL", 
    "Lake Zurich": "LKZ", 
    "Lakemoor": "ZZS", 
    "Lanark": "NAR", 
    "Lansing": "LSI", 
    "Lawrenceville": "LWV", 
    "Le Roy": "LRQ", 
    "Lebanon": "LVB", 
    "Lee": "LJE", 
    "Lemmon": "LMC", 
    "Lemont": "LMJ", 
    "Lena": "LEN", 
    "Lenox": "LXK", 
    "Lewistown": "L2T", 
    "Lexington": "LXT", 
    "Liberty": "IBX", 
    "Libertyville": "LBV", 
    "Lincoln": "LCL", 
    "Lincoln Park, Chicago": "LPD", 
    "Lincolnshire": "LCO", 
    "Lincolnwood": "LCW", 
    "Lindenhurst": "LH4", 
    "Lindenwood": "ZF9", 
    "Lisle": "LSA", 
    "Litchfield": "XHZ", 
    "Lockport": "LOT", 
    "Loda": "XWX", 
    "Logan, Edgar": "UZQ", 
    "Lombard": "LOM", 
    "London Mills": "L4O", 
    "Long Grove": "LGG", 
    "Longview": "JLG", 
    "Lostant": "UZT", 
    "Louisville": "ZF8", 
    "Loves Park": "QLI", 
    "Lynwood": "LYW", 
    "Lyons": "LYS", 
    "Macedonia": "M9Z", 
    "Machesney Park": "MP5", 
    "Mackinaw": "KWZ", 
    "Macomb": "MQB", 
    "Macon": "MO8", 
    "Madison": "MZX", 
    "Mahomet": "JMM", 
    "Makanda": "MK7", 
    "Malta": "TQM", 
    "Manhattan": "HM8", 
    "Manito": "ILT", 
    "Manteno": "MTR", 
    "Maple Park": "MEP", 
    "Mapleton": "XIS", 
    "Marengo": "REG", 
    "Marion": "MWA", 
    "Marissa": "JMA", 
    "Mark": "AWK", 
    "Markham": "MKM", 
    "Maroa": "MUR", 
    "Marseilles": "MR2", 
    "Marshall": "ML8", 
    "Martinsville": "IIE", 
    "Maryville": "YIB", 
    "Mascoutah": "MSK", 
    "Mason City": "M2C", 
    "Matteson": "AES", 
    "Mattoon": "MTO", 
    "Maywood/Chicago": "MWQ", 
    "Mazon": "MZF", 
    "McCook": "MCO", 
    "McGaw Park": "MWK", 
    "McHenry": "MHB", 
    "McLeansboro": "IMQ", 
    "Mechanicsburg": "HCG", 
    "Medinah": "EQH", 
    "Melrose Park": "MRP", 
    "Melvin": "ZVM", 
    "Mendota": "MEN", 
    "Meredoisa": "OIS", 
    "Meredosia": "VMS", 
    "Metamora": "EOA", 
    "Metropolis": "MET", 
    "Mettawa": "MT2", 
    "Michael": "MI7", 
    "Middleton": "MT3", 
    "Midlothian": "MLH", 
    "Midway": "DBD", 
    "Milan": "MIQ", 
    "Milford": "MFF", 
    "Milledgeville": "QLB", 
    "Millsdale": "KYA", 
    "Millstadt": "MS7", 
    "Minooka": "IKA", 
    "Mokena": "IMK", 
    "Moline": "MLI", 
    "Momence": "MME", 
    "Monee": "QZE", 
    "Monmouth": "MNI", 
    "Montgomery": "XIL", 
    "Monticello": "MQD", 
    "Morris": "MSW", 
    "Morrison": "MMQ", 
    "Morrisonville": "M5V", 
    "Morton": "MTI", 
    "Morton Grove": "MGV", 
    "Mossville": "MVJ", 
    "Mount Carmel": "MC6", 
    "Mount Carroll": "KRL", 
    "Mount Erie": "IUE", 
    "Mount Morris": "MXR", 
    "Mount Prospect": "MUP", 
    "Mount Pulaski": "MPK", 
    "Mount Sterling": "GTM", 
    "Mount Vernon": "MVN", 
    "Mount Zion": "UTZ", 
    "Moweaqua": "YMQ", 
    "Muncie": "MUB", 
    "Mundelein": "MUJ", 
    "Murdock": "MR5", 
    "Murphysboro": "M9U", 
    "Naperville": "NPV", 
    "Naples": "N6P", 
    "Nashville": "NXV", 
    "National City": "NCI", 
    "Neoga": "NE2", 
    "Neponset": "N8P", 
    "New Baden": "NDI", 
    "New Bedford": "EFC", 
    "New Haven": "NVQ", 
    "New Lenox": "NOX", 
    "New Salem": "NZS", 
    "Newark": "NKW", 
    "Newton": "NMQ", 
    "Niles": "NIL", 
    "Noble": "NO9", 
    "Normal": "NOM", 
    "Norridge": "NRF", 
    "Norris": "OZS", 
    "North Aurora": "NOA", 
    "North Barrington": "5NB", 
    "North Chicago": "NTA", 
    "North Riverside": "NRU", 
    "North Venice": "NVZ", 
    "Northbrook": "OBK", 
    "Northfield": "XJO", 
    "Northlake": "NTI", 
    "O'Fallon": "OFA", 
    "O'Hare Apt/Chicago": "ORD", 
    "Oak Brook": "QHO", 
    "Oak Forest": "OFR", 
    "Oak Grove": "QOG", 
    "Oak Lawn": "OKL", 
    "Oak Park": "QOP", 
    "Oakbrook Terrace": "OT2", 
    "Oakdale": "ODH", 
    "Oakland": "OUF", 
    "Oakley": "KLY", 
    "Ogden": "OGZ", 
    "Oglesby": "OGY", 
    "Ohio": "OH3", 
    "Okawville": "QXW", 
    "Olive Branch": "OQB", 
    "Olmsted": "OZM", 
    "Olney": "OLY", 
    "Olympia Fields": "OAN", 
    "Omaha": "OM3", 
    "Orangeville": "OAG", 
    "Oregon": "OGI", 
    "Orion": "OR2", 
    "Orland Park": "XKC", 
    "Osco": "OC3", 
    "Oswego": "OSG", 
    "Ottawa": "OTW", 
    "Palatine": "PLE", 
    "Palestine": "ZH4", 
    "Palos Heights": "P9H", 
    "Palos Hills": "PH5", 
    "Palos Park": "PP2", 
    "Pana": "PN2", 
    "Paris": "PRP", 
    "Park City": "PKC", 
    "Park Forest": "PFO", 
    "Park Ridge": "PKG", 
    "Pawnee": "PWE", 
    "Paxton": "PFB", 
    "Pearl City": "PEZ", 
    "Pecatonica": "ECT", 
    "Pekin": "PKI", 
    "Peoria": "PIA", 
    "Peoria Heights": "PHB", 
    "Peotone": "PJN", 
    "Peru": "VYS", 
    "Petersburg, Menard": "PB2", 
    "Pinckneyville": "YVP", 
    "Pingree Grove": "IEE", 
    "Piper City": "PC4", 
    "Pittsfield": "TFE", 
    "Plaines": "PLG", 
    "Plainfield": "PLI", 
    "Plano": "PNO", 
    "Pleasant Hill": "PT9", 
    "Pleasant Plains": "PPL", 
    "Plymouth": "YIQ", 
    "Polo": "POO", 
    "Pomona": "PQO", 
    "Pontiac": "POI", 
    "Pontoon Beach": "PNB", 
    "Posen": "PZO", 
    "Princeton": "PCO", 
    "Princeville": "PNZ", 
    "Prophetstown": "PPN", 
    "Prospect": "PP8", 
    "Prospect Heights": "PPG", 
    "Quincy": "UIN", 
    "Raleigh": "RA6", 
    "Rantoul": "RNL", 
    "Red Bud": "RRB", 
    "Richmond": "RMN", 
    "Richton Park": "RPJ", 
    "Ridgway": "RJW", 
    "Ridott": "RZT", 
    "Ringwood": "RIO", 
    "River Forest": "RVO", 
    "River Grove": "RG6", 
    "River Grove/Chicago": "RIG", 
    "Riverdale": "RRD", 
    "Riverside": "IVD", 
    "Riverton": "RN7", 
    "Riverwoods": "VWD", 
    "Roanoke": "RQX", 
    "Roberts": "R2O", 
    "Robinson": "ROB", 
    "Rochelle": "RCX", 
    "Rochester": "ROH", 
    "Rock City": "RC8", 
    "Rock Falls": "RFI", 
    "Rock Island": "RKI", 
    "Rockdale": "ROE", 
    "Rockford": "RFD", 
    "Rockport": "R63", 
    "Rockton": "RKT", 
    "Rockville Township": "R7P", 
    "Rockwood": "KOO", 
    "Rolling Meadows": "RLM", 
    "Romeoville": "ROI", 
    "Roodhouse": "RO3", 
    "Roscoe": "RSQ", 
    "Roselle": "RLL", 
    "Rosemont": "RSI", 
    "Rosiclaire": "RO9", 
    "Rosiclare": "RSK", 
    "Rossville": "RXL", 
    "Round Lake": "RUC", 
    "Round Lake Beach": "UDH", 
    "Round Lake Park": "ULP", 
    "Roxana": "RZM", 
    "Rushville": "R5E", 
    "Russell": "ZG2", 
    "Sadorus": "SD6", 
    "Saint Anne": "SE7", 
    "Saint Charles": "SSL", 
    "Saint Elmo": "EL5", 
    "Saint Joseph": "XLM", 
    "Salem": "SLO", 
    "Sandoval": "BMH", 
    "Sandwich": "SWH", 
    "Sauget": "SAU", 
    "Sauk Village": "SXL", 
    "Savanna": "SNQ", 
    "Savoy": "SYG", 
    "Scales Mound": "QJZ", 
    "Schaumburg": "JMH", 
    "Schiller Park": "SID", 
    "Scott Air Force Base": "SB3", 
    "Secor": "OZQ", 
    "Seneca": "XMI", 
    "Serena": "KSS", 
    "Seward": "QSR", 
    "Shelbyville": "SBV", 
    "Sheridan": "5SD", 
    "Sherrard": "SJK", 
    "Shiloh": "ILH", 
    "Shorewood": "SW3", 
    "Shumway": "UWX", 
    "Sidell": "SD3", 
    "Silvis": "ILV", 
    "Skokie": "SOK", 
    "Smithfield": "SM5", 
    "Somonauk": "SM7", 
    "South Barrington": "UHB", 
    "South Beloit": "SBL", 
    "South Chicago Heights": "OUS", 
    "South Elgin": "SE2", 
    "South Holland": "SUI", 
    "South Roxana": "RXS", 
    "Sparta": "SAR", 
    "Spring Grove": "SG3", 
    "Spring Valley": "SPN", 
    "Springfield": "SPI", 
    "Staunton": "UNT", 
    "Steeleville": "VTS", 
    "Steger": "SGQ", 
    "Sterling": "SGI", 
    "Sterling-Rockfalls Apt": "SQI", 
    "Stickney": "SKT", 
    "Stockton": "TC8", 
    "Stone Park": "OEK", 
    "Stonington": "SN6", 
    "Stookey": "SO9", 
    "Streamwood": "SMW", 
    "Streator": "STR", 
    "Sugar Grove": "S2G", 
    "Sullivan": "ULI", 
    "Summit": "ITG", 
    "Swansea": "SW6", 
    "Sycamore": "SYC", 
    "Tamms": "TMM", 
    "Tampico": "TMK", 
    "Taylorville": "TBD", 
    "Teutopolis": "TTX", 
    "Thomasboro": "TH9", 
    "Thomson": "TXN", 
    "Thornton": "THQ", 
    "Tilton": "TT3", 
    "Tinley Park": "TNL", 
    "Tiskilwa": "TKW", 
    "Toledo": "TQD", 
    "Tolono": "KUO", 
    "Toluca": "TLU", 
    "Tonica": "QTO", 
    "Topeka": "TQK", 
    "Tower Lakes": "TO7", 
    "Tremont": "TR9", 
    "Trenton": "TEQ", 
    "Trilla": "II9", 
    "Troy": "TGY", 
    "Troy Grove": "TYG", 
    "Tuscola": "XNH", 
    "Union": "UNZ", 
    "University Park": "UPK", 
    "Urbana": "URB", 
    "Utica": "UTQ", 
    "Valmeyer": "VYR", 
    "Vandalia": "VLA", 
    "Venice": "XNL", 
    "Vergennes": "VGX", 
    "Vermont": "VMN", 
    "Vernon": "VEQ", 
    "Vernon Hills": "VHI", 
    "Victoria": "VJO", 
    "Vienna": "VIE", 
    "Villa Grove": "VG9", 
    "Villa Park": "VPR", 
    "Virgil": "VRG", 
    "Virginia": "VGA", 
    "Volo": "VO2", 
    "Wadsworth": "QWO", 
    "Walnut Hill": "VTH", 
    "Warren": "WEN", 
    "Warrensburg": "JCQ", 
    "Warrenville": "XWV", 
    "Warsaw": "WXW", 
    "Wasco": "WO5", 
    "Washburn": "HBU", 
    "Washington": "WGI", 
    "Washington Park": "WGK", 
    "Waterloo": "ZTE", 
    "Waterman": "WTA", 
    "Watseka": "XOD", 
    "Wauconda": "WQN", 
    "Waukegan": "UGN", 
    "Wedron": "WRW", 
    "Weldon": "KDO", 
    "Wellington": "WCZ", 
    "West Chicago": "WCI", 
    "West Dundee": "WD8", 
    "West Frankfort": "KFT", 
    "West Peoria": "TPR", 
    "West Salem": "WS5", 
    "West Springfield": "WSU", 
    "Westchester": "ES3", 
    "Westmont": "WJO", 
    "Westville": "ZTV", 
    "Wheaton": "WHX", 
    "Wheeling": "WHE", 
    "White Hall": "WH6", 
    "Whittington": "WUG", 
    "Wicker Park": "WCP", 
    "Willow Brook": "WIB", 
    "Willow Springs": "WZG", 
    "Willowbrook, DuPage": "WOP", 
    "Wilmette": "XTT", 
    "Wilmington": "WQG", 
    "Wilsonville": "WL9", 
    "Winchester": "IHS", 
    "Windsor": "DZS", 
    "Winfield": "NFV", 
    "Winnebago": "WNN", 
    "Winnetka": "ZTK", 
    "Winslow": "WW7", 
    "Winthrop Harbor": "WPX", 
    "Wolf Lake": "WL8", 
    "Wonder Lake": "QOK", 
    "Wood Dale": "WDD", 
    "Wood River": "WRV", 
    "Woodhull": "WXU", 
    "Woodlawn": "WDI", 
    "Woodridge": "WOQ", 
    "Woodstock": "WOZ", 
    "Worden": "WI2", 
    "Worth": "WRH", 
    "Wyanet": "YAE", 
    "Wyoming": "YOJ", 
    "Yorkville": "YRV", 
    "Zion": "ZIO"
}