{
    "Aberdeen": "ABK", 
    "Adairville": "AD3", 
    "Albany": "AY9", 
    "Alexandria": "AXP", 
    "Allen": "AQ9", 
    "Annville": "VVY", 
    "Ashland": "ANL", 
    "Auburn": "A2U", 
    "Augusta": "AGU", 
    "Auxier": "KYX", 
    "Avon": "AVY", 
    "Barbourville": "BBZ", 
    "Bardstown": "XCV", 
    "Barlow": "KB5", 
    "Battletown": "TVW", 
    "Beattyville": "YVK", 
    "Beaver Dam": "BD3", 
    "Bedford": "VBD", 
    "Beech Grove": "GE3", 
    "Belfry": "QFR", 
    "Bellevue": "XDE", 
    "Belton": "BPL", 
    "Benton": "ZBO", 
    "Berea": "BEU", 
    "Berlin": "BR8", 
    "Berry": "AH8", 
    "Bethlehem": "BE5", 
    "Blaze": "KYB", 
    "Bloomfield": "BF8", 
    "Boston": "TQN", 
    "Bowling Green": "BWG", 
    "Brandenburg": "BNR", 
    "Breeding": "BG8", 
    "Brodhead": "BD8", 
    "Bromley": "BM3", 
    "Bronston": "TSZ", 
    "Brooklyn": "OYK", 
    "Brooks": "AFR", 
    "Brooksville": "VJL", 
    "Buckner": "CNW", 
    "Buechel": "UHU", 
    "Burkesville": "ZBV", 
    "Burlington": "BHJ", 
    "Burnside": "BD5", 
    "Butler": "BUJ", 
    "Cadiz": "YCZ", 
    "Calhoun": "CU3", 
    "Calvert City": "CCT", 
    "Campbellsburg": "CBU", 
    "Campbellsville": "CMP", 
    "Campton": "CTP", 
    "Carrollton": "CRK", 
    "Carter": "ZQR", 
    "Catlettsburg": "CGK", 
    "Cave City": "CCS", 
    "Cecilia": "JIA", 
    "Centertown": "CT8", 
    "Central City": "CUK", 
    "Chavies": "KYC", 
    "Cincinnati": "CI2", 
    "Clay": "UKY", 
    "Clay City": "CI8", 
    "Clermont": "CLO", 
    "Clifford": "QFF", 
    "Cloverport": "CVP", 
    "Cold Spring": "FCG", 
    "Columbia": "QOU", 
    "Columbus": "UQM", 
    "Conley": "7CE", 
    "Corbin": "CBI", 
    "Covington": "CVK", 
    "Coxs Creek": "C2C", 
    "Crestview Hills": "RHS", 
    "Crestwood": "CW7", 
    "Crittenden": "ITD", 
    "Crockett": "KHT", 
    "Crofton": "OFN", 
    "Cromwell": "C8W", 
    "Cumberland": "HXD", 
    "Cynthiana": "CAZ", 
    "Danville": "DVK", 
    "Dawson Springs": "DSG", 
    "Dayton": "DY2", 
    "Dixon": "KDX", 
    "Doe Run": "DOE", 
    "Dover": "DQV", 
    "Drakesboro": "DSB", 
    "Dry Ridge": "DDJ", 
    "Dunnville": "DNV", 
    "Earlington": "QEO", 
    "East Bernstadt": "ETD", 
    "East Point": "EPY", 
    "Eastwood": "ESZ", 
    "Eddyville": "EDV", 
    "Edgewood": "GHW", 
    "Edmonton": "EDC", 
    "Elizabethtown": "EKX", 
    "Elk Horn": "E3K", 
    "Elkton": "EKT", 
    "Eminence": "EN2", 
    "Erlanger": "ERL", 
    "Fairdale": "FIA", 
    "Falls of Rough": "KYF", 
    "Falmouth": "FQZ", 
    "Farmington": "FA3", 
    "Flemingsburg": "FMB", 
    "Florence": "FKY", 
    "Fordsville": "FSV", 
    "Fort Campbell": "FCM", 
    "Fort Knox": "FTK", 
    "Fort Mitchell": "FQK", 
    "Fort Thomas": "FHT", 
    "Fort Wright": "FWR", 
    "Frankfort": "FFT", 
    "Franklin": "FLK", 
    "Fredonia": "FGD", 
    "Fulton": "FTB", 
    "Georgetown": "GEO", 
    "Germantown": "GMQ", 
    "Ghent": "GHE", 
    "Glasgow": "GLW", 
    "Gordonville": "LLJ", 
    "Goshen": "GQH", 
    "Grahn": "KGY", 
    "Grand Rivers": "R8R", 
    "Gravel Switch": "UVW", 
    "Gray": "GYK", 
    "Grayson": "GYO", 
    "Greensburg": "AEH", 
    "Greenup": "ZDP", 
    "Greenville": "GVM", 
    "Grethel": "GTH", 
    "Guthrie": "GUH", 
    "Hagerhill": "HH2", 
    "Hanson": "HSK", 
    "Hardinsburg": "HXG", 
    "Harlan": "HR6", 
    "Harold": "A8N", 
    "Harrodsburg": "HBF", 
    "Hartford": "HTF", 
    "Hawesville": "HZZ", 
    "Hazard": "UJL", 
    "Hazel": "HZ2", 
    "Hazel Green": "AZE", 
    "Hebron": "HBN", 
    "Henderson": "XGD", 
    "Hestand": "HQ9", 
    "Hickman": "HM3", 
    "Hickory": "HIY", 
    "Hillview": "VIW", 
    "Hindman": "IXM", 
    "Hitchins": "KYH", 
    "Hodgenville": "HGQ", 
    "Hopkinsville": "HOP", 
    "Hustonville": "HUK", 
    "Hyden": "HYJ", 
    "Independence": "INP", 
    "Irvine": "IVK", 
    "Ivel": "IV8", 
    "Jackson": "JS3", 
    "Jamestown": "JMT", 
    "Jeffersontown": "JET", 
    "Jeffersonville": "ZJ9", 
    "Kansas": "KSJ", 
    "Kimper": "KPQ", 
    "La Center": "LZR", 
    "La Fayette": "LFE", 
    "La Grange": "LGR", 
    "LaFayette": "QLK", 
    "Lancaster": "LC5", 
    "Latonia": "LT2", 
    "Lawrenceburg": "LAQ", 
    "Lawrenceville": "LAV", 
    "Lebanon": "LFA", 
    "Lebanon Junction": "LJ2", 
    "Leitchfield": "LCF", 
    "Lewisburg": "LG7", 
    "Lewisport": "LWD", 
    "Lexington": "LEX", 
    "Liberty": "LY2", 
    "Livermore": "KKY", 
    "Logansport": "OGP", 
    "London": "LOZ", 
    "Loretto": "TKY", 
    "Louisa": "KZY", 
    "Louisville": "LUI", 
    "Lowmansville": "LQL", 
    "Ludlow": "LLW", 
    "Lyndon": "JYN", 
    "Maceo": "MKP", 
    "Madisonville": "MVQ", 
    "Manchester": "MCX", 
    "Marion": "IJN", 
    "Marrowbone": "MWZ", 
    "Martin": "ZAR", 
    "Mayfield": "MAY", 
    "Maysville": "MVU", 
    "Means": "QMS", 
    "Middlesboro": "MBR", 
    "Midway": "M23", 
    "Millersburg": "ILB", 
    "Millwood": "IOO", 
    "Minnie": "MX8", 
    "Mize": "XIZ", 
    "Monticello": "MOC", 
    "Moorefield": "MF2", 
    "Morehead": "MHR", 
    "Morganfield": "QGF", 
    "Morgantown": "MGG", 
    "Mortons Gap": "MJJ", 
    "Mount Sterling": "MGK", 
    "Mount Vernon": "MXV", 
    "Mount Washington": "UMX", 
    "Mouthcard": "MC7", 
    "Munfordville": "UNF", 
    "Murray": "CEY", 
    "New Castle": "JWC", 
    "Newport": "XJU", 
    "Nicholasville": "NCK", 
    "Nortonville": "OJV", 
    "Olive Hill": "OHF", 
    "Owensboro": "OWB", 
    "Owenton": "QOW", 
    "Owingsville": "O2W", 
    "Paducah": "PAH", 
    "Paintsville": "PAI", 
    "Paris": "PZT", 
    "Park City": "PC6", 
    "Parkers Lake": "PA4", 
    "Petersburg": "RUG", 
    "Pewee Valley": "EYC", 
    "Phelps": "IPP", 
    "Philpot": "PPP", 
    "Pikeville": "PKK", 
    "Pine Knot": "IKN", 
    "Pleasure Ridge Park": "PGK", 
    "Pleasureville": "EIU", 
    "Prestonsburg": "PB3", 
    "Princeton": "PNK", 
    "Prospect": "POP", 
    "Providence, Webster": "VDC", 
    "Raceland": "RXA", 
    "Radcliff": "QRD", 
    "Richmond": "RHM", 
    "Richwood": "RWO", 
    "Robards": "RBA", 
    "Rockfield": "YIC", 
    "Rush": "RQY", 
    "Russell": "RKU", 
    "Russell Springs": "RS5", 
    "Russellville": "RVK", 
    "Salvisa": "DQA", 
    "Salyersville": "ZSK", 
    "Science Hill": "HL9", 
    "Scottsville": "SCV", 
    "Sebree": "YSB", 
    "Shelbyville": "SVZ", 
    "Shepherdsville": "SQN", 
    "Shively": "IVE", 
    "Sidney": "S7I", 
    "Silver Grove": "VKY", 
    "Simpsonville": "SIJ", 
    "Smithfield": "SDE", 
    "Smiths Grove": "SK6", 
    "Somerset": "SME", 
    "Sonora": "KTY", 
    "South Shore": "SSH", 
    "South Union": "YSU", 
    "Southgate": "OUH", 
    "Springfield": "RNF", 
    "Stamping Ground": "9SG", 
    "Stanford": "TAN", 
    "Stanton": "SX8", 
    "Sturgis": "TUG", 
    "Summer Shade": "SU4", 
    "Symsonia": "YMO", 
    "Taylor Mill": "YLI", 
    "Taylorsville": "YLV", 
    "Tompkinsville": "TPM", 
    "Trenton": "TXE", 
    "Turners Station": "TUO", 
    "Union": "UN7", 
    "Uniontown": "UT2", 
    "Vanceburg": "VGS", 
    "Verona": "VRO", 
    "Versailles": "VSS", 
    "Vicco": "VQO", 
    "Vine Grove": "VGR", 
    "Virgie": "3VR", 
    "Wallingford": "YGF", 
    "Walton": "QWT", 
    "Warsaw": "WZS", 
    "West Liberty": "WLH", 
    "White Plains": "W7P", 
    "Whitesburg": "BRG", 
    "Whitley City": "W2K", 
    "Whitner": "WHK", 
    "Wickliffe": "WKY", 
    "Wilder": "WII", 
    "Williamsburg": "WBK", 
    "Williamstown": "WS8", 
    "Winchester": "WIN", 
    "Wolf Creek": "WZB", 
    "Woodburn": "TVN", 
    "Woodman": "WK7", 
    "Woorburn": "OEF", 
    "Wurtland": "WUR"
}