{
    "Aldeanueva del Codonal": "AD2", 
    "Ayllon": "AYN", 
    "Cantalejo": "CLJ", 
    "Carbonero el Mayor": "W4J", 
    "Castillejo de Mesleon": "CTM", 
    "Coca": "OAC", 
    "Duruelo": "DUO", 
    "Fuente el Olmo de Fuentidue\u00f1a": "FOM", 
    "Fuentepelayo": "FUP", 
    "Hontoria": "HON", 
    "Huerta": "HT4", 
    "La Lastrilla": "RI9", 
    "Mozoncillo": "MCZ", 
    "Mudri\u00e1n": "MUD", 
    "Nava Asuncion": "NAC", 
    "Navalmanzano": "NMZ", 
    "Navas de Oro": "NAO", 
    "Nieva": "SN8", 
    "Olombrada": "DFE", 
    "Otero de Herreros": "OHS", 
    "Pinarejos": "PIN", 
    "Riaza": "RIZ", 
    "Sacramenia": "SMN", 
    "San Ildefonso": "SFJ", 
    "Sanchonu\u00f1o": "SNO", 
    "Santa Maria Real Nieva": "SRN", 
    "Sepulveda": "SPU", 
    "Tabanera la Luenga": "TBL", 
    "Torrecaballeros": "TCS", 
    "Turegano": "TRG", 
    "Vallelado": "VED", 
    "Valtiendas": "DAX", 
    "Valverde del Majano": "VDM", 
    "Zarzuela del Pinar": "ZZP"
}