{
    "'t Waar": "TWA", 
    "Aduard": "ADU", 
    "Bierum": "BIR", 
    "Borgsweer": "BGW", 
    "Bourtange": "BTA", 
    "Den Ham": "DHM", 
    "Doodstil": "DSI", 
    "Eelde": "LDE", 
    "Ellerhuizen": "ELZ", 
    "Fraamklap": "FKP", 
    "Gaarkeuken": "GKN", 
    "Garmerwolde": "GWO", 
    "Grootegast": "GTG", 
    "Haren": "HRE", 
    "Heiligerlee": "HEI", 
    "Hoogkerk": "HKK", 
    "Kantens": "KTN", 
    "Kolham": "KHA", 
    "Kommerzijl": "KML", 
    "Kornhorn": "ZAN", 
    "Lageland": "LGD", 
    "Lalleweer": "LWE", 
    "Lauwerzijl": "LWI", 
    "Leens": "LES", 
    "Loppersum": "LPM", 
    "Maarhuizen": "MHU", 
    "Meeden": "MEK", 
    "Mensingeweer": "MSW", 
    "Middelstum": "MDU", 
    "Midwolda": "MWD", 
    "Musselkanaal": "MUS", 
    "Nieuw-Scheemda": "NSD", 
    "Nieuwe Pekela": "NPK", 
    "Nieuwe Statenzijl": "NSZ", 
    "Nieuweschans": "NSC", 
    "Nieuwolda": "NWO", 
    "Niezijl": "NZI", 
    "Noordwijk": "NDW", 
    "Oldehove": "OLE", 
    "Overschild": "OSK", 
    "Pieterzijl": "PZI", 
    "Scheemderzwaag": "SMZ", 
    "Schildwolde": "SDW", 
    "Schouwerzijl": "SWL", 
    "Slochteren": "SLO", 
    "Ten Boer": "NTO", 
    "Ten Post": "TPT", 
    "Termunten": "TMN", 
    "Termunterzijl": "TMZ", 
    "Tolbert": "TOL", 
    "Usquert": "NPZ", 
    "Vierverlaten": "VVL", 
    "Visvliet": "VSI", 
    "Vlagtwedde": "VWD", 
    "Vries": "VIS", 
    "Warfhuizen": "WHU", 
    "Waterhuizen": "WHZ", 
    "Wehe-den Hoorn": "WHO", 
    "Westbroek": "WBO", 
    "Westerbroek": "WBR", 
    "Winsum": "WNS", 
    "Zevenhuizen": "ZVH", 
    "Zuidbroek": "ZBO", 
    "Zuidhorn": "ZUI", 
    "Zuidwolde": "ZWL"
}