{
    "Annfield Plain": "ANP", 
    "Aycliffe": "AYF", 
    "Barnard Castle": "BCA", 
    "Bishop Auckland": "BIP", 
    "Blackhall Colliery": "BKI", 
    "Bowburn": "BWN", 
    "Burnopfield": "DUO", 
    "Chester-le-Street": "CTE", 
    "Chilton": "CHO", 
    "Consett": "CNT", 
    "Crook": "ZAU", 
    "Darlington": "DRL", 
    "Durham": "DRH", 
    "Easington": "ESG", 
    "Ferryhill": "FRY", 
    "Fishburn": "XFH", 
    "Greencroft": "GCX", 
    "Heighington": "HEI", 
    "Howden le Wear": "XHN", 
    "Hunwick": "HUN", 
    "Lanchester": "XTL", 
    "Ludworth": "LUW", 
    "Newton Aycliffe": "NAY", 
    "Peterlee": "PTE", 
    "Rowlands Gill": "RGI", 
    "Seaham": "SEA", 
    "Seal Sands": "XSS", 
    "Sedgefield": "SGE", 
    "Sherburn": "SBN", 
    "Shildon": "SDN", 
    "Shotton": "SHT", 
    "Spennymoor": "SPN", 
    "Stanhope": "SOP", 
    "Stanley": "SNL", 
    "Thornley": "NLE", 
    "Tow Law": "TWW", 
    "Trimdon Grange": "TGR", 
    "Wear Head": "WHD", 
    "West Auckland": "WAX", 
    "Westgate": "WXW", 
    "Wingate": "WIA"
}