{
    "A'Chill": "ACI", 
    "Acharacle": "ACA", 
    "Achiltibuie": "ACE", 
    "Alness": "ASS", 
    "Applecross": "APS", 
    "Ardersier": "ARS", 
    "Ardgour": "AGU", 
    "Ardnamurchan": "AMN", 
    "Arisaig": "ARG", 
    "Armadale, Isle of Skye": "AMD", 
    "Arnish": "RAA", 
    "Auckengill": "AKL", 
    "Aultbea": "AUL", 
    "Aviemore": "AIE", 
    "Avoch": "AVC", 
    "Balintore": "BLI", 
    "Ballachulish": "BCU", 
    "Balmacara": "BMC", 
    "Balnabruaich": "LBC", 
    "Beauly": "BBL", 
    "Berriedale": "ERR", 
    "Boat of Garten": "GAN", 
    "Bracadale": "RCD", 
    "Bracora": "ZRC", 
    "Breakish": "BKK", 
    "Broadford, Isle of Skye": "BDF", 
    "Brora": "BRJ", 
    "Camusnagaul": "CAU", 
    "Canna, Inner Hebrides": "CNA", 
    "Cannich": "CNI", 
    "Carbost": "CAB", 
    "Carloway": "RLW", 
    "Carrbridge": "CBD", 
    "Carron": "RRO", 
    "Castletown": "CTN", 
    "Clachan, Raasay": "RAS", 
    "Cononbridge": "CGR", 
    "Corpach": "COR", 
    "Cromarty": "CRN", 
    "Crosskirk": "CKK", 
    "Croy": "ZAV", 
    "Culkein": "CKN", 
    "Culkein/Drumbeg": "CLM", 
    "Dalwhinnie": "DWI", 
    "Dingwall": "DIW", 
    "Dornoch": "DOC", 
    "Drumfearn": "KIE", 
    "Dunbeath": "DUE", 
    "Dunvegan": "DVN", 
    "Durness": "DNS", 
    "Elgol, Isle of Skye": "EGO", 
    "Erribol": "RBL", 
    "Evanton": "EVT", 
    "Foindlemore - Loch Glendhu": "FOI", 
    "Forsinard": "FON", 
    "Fort Augustus": "FAU", 
    "Fort William": "FWM", 
    "Fortrose": "FTR", 
    "Gairloch": "GAR", 
    "Galmisdale, Eigg": "GAS", 
    "Garve": "GAV", 
    "Gills": "ILL", 
    "Glenelg": "GNL", 
    "Glenfinnan": "GFN", 
    "Glensanda": "GSA", 
    "Glenuig": "GLG", 
    "Golspie": "GLP", 
    "Grantown-on-Spey": "GOY", 
    "Halkirk": "HKI", 
    "Helmsdale": "HMA", 
    "Invergarry": "INY", 
    "Invergordon": "IVG", 
    "Inverie": "INR", 
    "Inverness": "INV", 
    "Isle of Skye": "ISK", 
    "John O'Groats": "JOG", 
    "Keiss": "KES", 
    "Kilchoan": "KOA", 
    "Kilmore": "TKV", 
    "Kinbrace": "KIA", 
    "Kingussie": "KGU", 
    "Kinloch, Rum": "KOH", 
    "Kinlochbervie": "KBE", 
    "Kirtomy": "KRM", 
    "Kishorn": "KIS", 
    "Kyle of Lochalsh": "KYL", 
    "Kyleakin": "KYN", 
    "Kylesku": "KYU", 
    "Lairg": "LRG", 
    "Latheronwheel": "LWL", 
    "Loch Torridon": "LCD", 
    "Lochailort": "LCI", 
    "Lochaline": "LOL", 
    "Lochcarron": "LCR", 
    "Lochinver": "LOV", 
    "Luibeilt": "LUB", 
    "Lybster": "LYB", 
    "Mallaig": "MLG", 
    "Meikle Ferry": "MFY", 
    "Muir of Ord": "MOO", 
    "Munlochy": "MHY", 
    "Nairn": "NAI", 
    "Nethy Bridge": "NBI", 
    "Newtonmore": "NEN", 
    "Nigg": "NGG", 
    "Old Dornie": "ODO", 
    "Plockton": "PLO", 
    "Poolewe": "PWE", 
    "Port Mor, Muck": "PMR", 
    "Portmahomack": "PMK", 
    "Portnalong": "PNG", 
    "Portree": "PRT", 
    "Portskerra": "PKA", 
    "Reay": "REA", 
    "Rhilochan": "RHI", 
    "Rhu Coigach - Badluachrach": "RCB", 
    "Rosemarkie": "RME", 
    "Roybridge": "ROB", 
    "Rudh Re - Red Point": "RDH", 
    "Salen": "AEN", 
    "Sandside": "SDS", 
    "Scarfskerry": "SFK", 
    "Sconser, Isle of Skye": "SCO", 
    "Scourie": "RIE", 
    "Scrabster": "SCR", 
    "Shieldaig": "SHX", 
    "Shinness": "SYL", 
    "Skerray": "SKR", 
    "Sleat": "ATS", 
    "Snizort": "SZT", 
    "Spean Bridge": "ZSB", 
    "Staxigoe": "SXE", 
    "Strathaird": "SRH", 
    "Strathcarron": "SRC", 
    "Strathpeffer": "FFR", 
    "Stroma": "SOA", 
    "Tain": "TIN", 
    "Talmine": "TLN", 
    "Thurso": "THR", 
    "Tomatin": "TOA", 
    "Tongue": "TGU", 
    "Torridon": "TRD", 
    "Uig": "UIG", 
    "Ullapool": "ULL", 
    "Whaligoe": "WLG", 
    "Wick": "WIC"
}