{
    "Aubiet": "ABI", 
    "Auch": "AUC", 
    "Avensac": "AJC", 
    "Ayguetinte": "AGN", 
    "Bajonnette": "BJT", 
    "Bassoues": "XF4", 
    "Beaucaire": "BCR", 
    "Bezeril": "2BZ", 
    "Blanquefort": "BLQ", 
    "Bretagne-d'Armagnac": "NED", 
    "Campagne-d'Armagnac": "CPD", 
    "Cannet": "CAX", 
    "Cassaigne": "G32", 
    "Castelnau-Dauzan": "ZZA", 
    "Castera-Verduzan": "GVG", 
    "Castex": "TXX", 
    "Castex-d'Armagnac": "XCX", 
    "Caupenne-d'Armagnac": "CD3", 
    "Cazaubon": "CZC", 
    "Cazeneuve": "ZUV", 
    "Condom": "COD", 
    "Courrensan": "URF", 
    "Eauze": "EAZ", 
    "Fleurance": "FLU", 
    "Fources": "FRG", 
    "Gimont": "GIM", 
    "Gondrin": "GND", 
    "J\u00e9gun": "JGA", 
    "L'Isle-Jourdain": "LJN", 
    "L'Isle-de-Noe": "SKE", 
    "La Romieu": "LRM", 
    "Labarthete": "REX", 
    "Lagarde-Hachan": "LHN", 
    "Lagraulet-du-Gers": "PGL", 
    "Lannemaignan": "WLJ", 
    "Lannepax": "WLK", 
    "Laree": "XEE", 
    "Larroque-sur-l'Osse": "XSS", 
    "Laujuzan": "LJZ", 
    "Lauraet": "LU4", 
    "Le Houga": "HGA", 
    "Lectoure": "LE3", 
    "Lias-d'Armagnac": "QWE", 
    "Lombez": "G3Z", 
    "Manciet": "MC2", 
    "Marambat": "MBP", 
    "Marciac": "CC9", 
    "Maul\u00e9on-d'Armagnac": "GJD", 
    "Mauvezin": "ZMJ", 
    "Mirande": "MJK", 
    "Mirepoix": "MPX", 
    "Monferran-Plav\u00e8s": "MPV", 
    "Monguilhem": "YUP", 
    "Monlezun-d'Armagnac": "MD4", 
    "Montesquiou": "NTQ", 
    "Montestruc-sur-Gers": "MUU", 
    "Montr\u00e9al-du-Gers": "GGZ", 
    "Mont\u00e9gut-Arros": "MOA", 
    "Morm\u00e8s": "MM7", 
    "Mouchan": "M2C", 
    "Nogaro": "NRO", 
    "Orn\u00e9zan": "OZM", 
    "Panjas": "PJR", 
    "Plaisance": "PN4", 
    "Ramouzens": "RZZ", 
    "Rejaumont": "ONJ", 
    "Riguepeu": "RI8", 
    "Riscle": "RIS", 
    "Roquelaure": "QJE", 
    "Roques": "RQV", 
    "R\u00e9ans": "QJK", 
    "Saint-Aunix-Lengros": "SQ5", 
    "Saint-Clar": "ZHI", 
    "Saint-Germ\u00e9": "TGE", 
    "Saint-Jean-Poutge": "SJP", 
    "Saint-Martin-d'Armagnac": "MA5", 
    "Saint-Mont": "TMO", 
    "Saint-Puy": "YPZ", 
    "Sainte-Christie": "PYT", 
    "Sainte-Christie-d'Armagnac": "IMC", 
    "Sainte-Lizaigne": "LZ3", 
    "Samatan": "SKT", 
    "Sarragachies": "GXG", 
    "Seysses-Sav\u00e8s": "S2S", 
    "Sorbets": "ORB", 
    "S\u00e9goufielle": "SEG", 
    "Troncens": "4TG", 
    "Valence-sur-Ba\u00efse": "VS5", 
    "Vic-Fezensac": "HT8", 
    "Viella": "VG3"
}