{
    "Aach": "AAC", 
    "Aalen": "AAL", 
    "Abstatt": "ABA", 
    "Abtsgm\u00fcnd": "AGD", 
    "Achberg": "AC2", 
    "Achern": "ACH", 
    "Achstetten": "ACT", 
    "Adelberg-Dorf": "ADB", 
    "Adelmannsfelden": "AD5", 
    "Adelsheim": "ADH", 
    "Adrazhofen": "AZH", 
    "Affalterbach": "AFB", 
    "Aglasterhausen": "AGX", 
    "Ahorn": "AHW", 
    "Aich": "AIH", 
    "Aichelberg": "ABG", 
    "Aichhalden": "AHD", 
    "Aichstetten": "AIB", 
    "Aichtal": "AIL", 
    "Aichwald": "AWD", 
    "Aidlingen": "AII", 
    "Aitern": "AIU", 
    "Aitrach": "AIT", 
    "Albbruck": "ABK", 
    "Albershausen": "ALE", 
    "Albstadt": "ALB", 
    "Aldingen": "ALN", 
    "Alfdorf": "ARF", 
    "Algishofen": "AA4", 
    "Allensbach": "A7A", 
    "Alleshausen": "2AA", 
    "Allmannsweiler": "5AA", 
    "Allmendingen": "AED", 
    "Allmersbach im Tal": "7AA", 
    "Alpirsbach": "ASB", 
    "Altbach": "ABC", 
    "Altdorf": "AKB", 
    "Altenbach, Schriesheim": "6AG", 
    "Altenheim": "77R", 
    "Altenriet": "2AJ", 
    "Altensteig": "ASG", 
    "Altheim bei Ehingen": "9AK", 
    "Altheim bei Riedlingen": "7AK", 
    "Altheim, Alb": "8AK", 
    "Althengstett": "AET", 
    "Althuette": "AQE", 
    "Altlussheim": "ALM", 
    "Altshausen": "ATS", 
    "Ammerbuch": "AMM", 
    "Amstetten": "7AP", 
    "Amtzell": "ATZ", 
    "Angelbachtal": "6AQ", 
    "Appensee": "3AT", 
    "Appenweier": "APW", 
    "Appenweiler": "AWE", 
    "Argenb\u00fchl": "AQL", 
    "Aspach": "APH", 
    "Asperg": "APG", 
    "Assamstadt": "ASA", 
    "Asselfingen": "2AZ", 
    "Attenweiler": "A45", 
    "Au": "AUI", 
    "Au am Rhein": "AUH", 
    "Auenwald": "UAD", 
    "Auggen": "AGQ", 
    "Auhof": "A73", 
    "Aulendorf": "AUL", 
    "Backnang": "BAC", 
    "Bad Bellingen": "BBB", 
    "Bad Boll": "BBO", 
    "Bad Ditzenbach": "BDZ", 
    "Bad Durrheim": "RHX", 
    "Bad Friedrichshall": "BFH", 
    "Bad Herrenalb": "BE5", 
    "Bad Krozingen": "BDK", 
    "Bad Liebenzell": "LBZ", 
    "Bad Mergentheim": "BME", 
    "Bad Peterstal-Griesbach": "BPT", 
    "Bad Rappenau": "BPP", 
    "Bad Rippoldsau-Schapbach": "BRP", 
    "Bad Saulgau": "BSG", 
    "Bad Schussenried": "BSR", 
    "Bad Sch\u00f6nborn": "BSN", 
    "Bad S\u00e4ckingen": "BSA", 
    "Bad Urach": "URH", 
    "Bad Waldsee": "BWS", 
    "Bad Wildbad": "BWB", 
    "Bad Wimpfen": "BWF", 
    "Bad Wurzach": "BWZ", 
    "Bad \u00dcberkingen": "BUK", 
    "Baden Baden": "BAB", 
    "Badenweiler": "BJ4", 
    "Badisch Sch\u00f6llenbach": "BJ7", 
    "Baechingen": "ZNB", 
    "Bahlingen": "BEZ", 
    "Bahlingen Am Kaiserstuhl": "BAO", 
    "Baienfurt": "BFT", 
    "Baiersbronn": "BRR", 
    "Baindt": "BXT", 
    "Balgheim": "BN3", 
    "Balingen": "BAL", 
    "Ballendorf/W\u00fcrttemberg": "BN6", 
    "Ballrechten": "TEJ", 
    "Baltmannsweiler": "BQR", 
    "Baltringen": "QBL", 
    "Balzheim": "BZJ", 
    "Bammental": "BTH", 
    "Bartholom\u00e4": "BV9", 
    "Bauschlott": "78E", 
    "Beckstein": "BQK", 
    "Beihingen": "IGN", 
    "Beilstein/W\u00fcrttemberg": "B4I", 
    "Beimerstetten": "BM3", 
    "Bempflingen": "BMP", 
    "Benningen Am Neckar": "BGK", 
    "Berg (Ravensburg)": "BKV", 
    "Bergatreute": "B2R", 
    "Berghaupten": "BHP", 
    "Bergh\u00fclen": "BEJ", 
    "Berkheim": "B5V", 
    "Bermatingen": "BMN", 
    "Bernau": "RNA", 
    "Bernau im Schwarzwald": "UIS", 
    "Berneck bei Geislingen an der Steige": "B4X", 
    "Bernhalden": "B5X", 
    "Bernried": "BXX", 
    "Bernstadt/W\u00fcrttemberg": "B8Y", 
    "Besigheim": "BEM", 
    "Betzenweiler": "9BC", 
    "Betzweiler": "BZW", 
    "Beuren": "RUX", 
    "Beuron": "3BE", 
    "Biberach": "BIB", 
    "Biberach an der Riss": "IAD", 
    "Bieringen": "BYI", 
    "Bietigheim": "BEE", 
    "Bietigheim-Bissingen": "BBI", 
    "Billigheim": "BGI", 
    "Binau": "8BK", 
    "Bingen bei Sigmaringen": "IBI", 
    "Binzen": "BIZ", 
    "Birach": "CHH", 
    "Birenbach": "BNC", 
    "Birkenfeld": "BIF", 
    "Bischweier": "BIS", 
    "Bisingen": "BWK", 
    "Bissingen an der Teck": "6BQ", 
    "Bitz": "BQZ", 
    "Blaubeuren": "BLE", 
    "Blaufelden": "BLF", 
    "Blaustein": "BLS", 
    "Blumberg": "BLU", 
    "Bodelshausen": "BHS", 
    "Bodman": "BLW", 
    "Bodnegg": "BDN", 
    "Boll": "OLL", 
    "Bollschweil": "BLL", 
    "Boms": "42B", 
    "Bondorf/Boblingen": "BOO", 
    "Bonndorf im Schwarzwald": "ZBD", 
    "Bopfingen": "BOP", 
    "Bortlingen": "OLG", 
    "Boxberg": "BXB", 
    "Brackenheim": "BCM", 
    "Brandhof": "B94", 
    "Braunsbach": "235", 
    "Breisach": "BSH", 
    "Breitenstein": "BII", 
    "Breitingen": "EGX", 
    "Breitnau": "BRQ", 
    "Bretten": "BTN", 
    "Brettenfeld": "79Z", 
    "Bretzfeld": "BZF", 
    "Brigachtal": "BG5", 
    "Brombach bei Eberbach/Baden": "ORQ", 
    "Bruchhausen": "BHH", 
    "Bruchsal": "BCL", 
    "Br\u00e4unlingen": "BRY", 
    "Bubsheim": "BSI", 
    "Buch/Schw\u00e4bisch Hall": "UCW", 
    "Buchen": "BUC", 
    "Buchenbach": "BQH", 
    "Buchheim": "UCM", 
    "Buggingen": "UG4", 
    "Buhlenhausen": "UAE", 
    "Burg Hohenzollern": "GZ2", 
    "Burgrieden": "BUJ", 
    "Burgstetten": "BUS", 
    "Burladingen": "URR", 
    "B\u00e4renthal": "B4J", 
    "B\u00f6bingen an der Rems": "4BZ", 
    "B\u00f6blingen": "BWU", 
    "B\u00f6hmenkirch": "BMC", 
    "B\u00f6llen": "22B", 
    "B\u00f6nnigheim": "OGM", 
    "B\u00f6rslingen": "B33", 
    "B\u00f6singen": "B52", 
    "B\u00f6ttingen": "B66", 
    "B\u00f6tzingen": "BTZ", 
    "B\u00fchl": "BUL", 
    "B\u00fchlertal": "BLT", 
    "B\u00fchlertann": "BTX", 
    "B\u00fchlerzell": "BR6", 
    "B\u00fchlerzimmern": "BYM", 
    "B\u00fcrchau": "BJJ", 
    "B\u00fcsingen": "US2", 
    "Calw": "CAL", 
    "Cleebronn": "CLV", 
    "Crailsheim": "CRH", 
    "Creglingen": "CGL", 
    "Daisendorf": "DSJ", 
    "Dauchingen": "DUG", 
    "Deckenpfronn": "DPF", 
    "Deggenhausertal": "DBW", 
    "Deggingen": "79E", 
    "Deilingen": "DGE", 
    "Deisslingen": "DLI", 
    "Deizisau": "DZU", 
    "Dellmensingen": "DMZ", 
    "Denkendorf": "DKF", 
    "Denkingen": "77Z", 
    "Denzlingen": "DZN", 
    "Dettenhausen": "DAE", 
    "Dettenheim": "DNH", 
    "Dettighofen": "DFN", 
    "Dettingen": "DTG", 
    "Dettingen an der Erms": "DEM", 
    "Dettingen an der Iller": "DTI", 
    "Dettingen unter Teck": "DUT", 
    "Diedesheim/Mosbach": "MDD", 
    "Dielheim": "DHE", 
    "Diersheim": "DHM", 
    "Dietenheim": "DNM", 
    "Dietingen": "DII", 
    "Dischingen": "DCG", 
    "Ditzingen": "DTN", 
    "Dogern": "DOG", 
    "Donaueschingen": "DEN", 
    "Donautal": "DNU", 
    "Donzdorf": "DZD", 
    "Dormettingen": "ZND", 
    "Dornhan": "DNW", 
    "Dornstadt": "DST", 
    "Dornstetten": "DSN", 
    "Dossenheim": "DSM", 
    "Dotternhausen": "TNA", 
    "Dottingen (Ballrechten-Dottingen)": "BO3", 
    "Drackenstein": "DKT", 
    "Dunningen": "UNG", 
    "Durbach": "DUR", 
    "Durchhausen": "78A", 
    "Durlangen": "DR3", 
    "Durmersheim": "DUM", 
    "Dusslingen": "DUL", 
    "D\u00f6ffingen": "79C", 
    "D\u00f6rzbach": "DZB", 
    "D\u00fcrbheim": "DBH", 
    "D\u00fcrmentingen": "DMT", 
    "D\u00fcrnau": "DNA", 
    "Eberbach": "EBB", 
    "Eberdingen": "EBZ", 
    "Eberhardzell": "ZEB", 
    "Ebersbach an der Fils": "EBE", 
    "Ebersbach-Musbach": "EMH", 
    "Eberstadt": "EER", 
    "Ebhausen": "EQN", 
    "Ebnat": "EB4", 
    "Ebringen": "EBN", 
    "Eckartshausen": "ECQ", 
    "Edingen": "EDI", 
    "Edingen-Neckarhausen": "ECN", 
    "Efringen-Kirchen": "EFK", 
    "Egenhausen": "EHU", 
    "Egesheim": "EGY", 
    "Eggenstein-Leopoldshafen": "EGL", 
    "Eggingen": "EGE", 
    "Ehingen": "EHI", 
    "Ehningen": "EHG", 
    "Ehrenkirchen": "EHK", 
    "Eichstetten": "EST", 
    "Eigeltingen": "ZNI", 
    "Eimeldingen": "EDG", 
    "Eisenbach": "EHO", 
    "Eislingen": "ELN", 
    "Elgersweier": "EIE", 
    "Ellhofen": "79M", 
    "Ellwangen": "ELW", 
    "Elzach": "EZH", 
    "Elztal": "ELL", 
    "Emmendingen": "EMN", 
    "Emmingen-Liptingen": "ELI", 
    "Empfingen": "EFG", 
    "Endingen": "END", 
    "Engelsbrand": "EBD", 
    "Engen": "ENE", 
    "Engstingen": "EGT", 
    "Eningen unter Achalm": "ZME", 
    "Eppelheim": "EPP", 
    "Eppingen": "EPI", 
    "Erbach": "EBS", 
    "Erdmannhausen": "ERM", 
    "Eriskirch": "ERI", 
    "Erlenbach": "EBH", 
    "Erlenbach (Heilbronn)": "ERO", 
    "Erligheim": "EXM", 
    "Erolzheim": "RZH", 
    "Ertingen": "EKB", 
    "Erzgebirge": "BS2", 
    "Eschach": "EHC", 
    "Eschach (bei Schw\u00e4bisch Gm\u00fcnd)": "ESA", 
    "Eschbach": "EBA", 
    "Eschbach (Markgr\u00e4flerland)": "EQD", 
    "Eschbronn": "EZB", 
    "Eschelbronn": "ESQ", 
    "Eschenbach": "EHB", 
    "Esseratsweiler": "EWL", 
    "Essingen": "EGN", 
    "Esslingen": "ESL", 
    "Ettenheim": "ETI", 
    "Ettlingen": "ETT", 
    "Eutingen": "ETG", 
    "Fahrenbach": "5FA", 
    "Feldberg (Schwarzwald)": "77C", 
    "Fellbach": "FBH", 
    "Fichtenau": "FIH", 
    "Fichtenberg": "FNB", 
    "Filderstadt": "FIL", 
    "Fischbach": "FHB", 
    "Fischerbach": "FSX", 
    "Flein": "79I", 
    "Fluorn": "FBW", 
    "Forbach": "FBC", 
    "Forchheim": "FRM", 
    "Forchtenberg": "FTB", 
    "Forst": "FOB", 
    "Frankenbach": "FRC", 
    "Frankenhardt": "FKT", 
    "Freiberg am Neckar": "FEG", 
    "Freiburg im Breisgau": "FBG", 
    "Freiburg im Breisgau-Betzenhausen": "7BC", 
    "Freistett": "FES", 
    "Freudenberg": "FRH", 
    "Freudenstadt": "FST", 
    "Freudental": "FDL", 
    "Frickenhausen": "FKH", 
    "Frickingen": "ZDV", 
    "Fridingen": "FDG", 
    "Friedenweiler": "FWR", 
    "Friedrichshafen": "FDH", 
    "Friesenheim (Baden)": "FXM", 
    "Friolzheim": "FIO", 
    "Frittlingen": "FTT", 
    "Furtwangen": "FWN", 
    "Gaggenau": "GAG", 
    "Gaienhofen": "77I", 
    "Gaildorf": "GAI", 
    "Gailingen": "GAE", 
    "Gaisbach": "GAC", 
    "Gammelshausen": "GLS", 
    "Gammertingen": "GTG", 
    "Gechingen": "GEC", 
    "Geisingen": "ZGB", 
    "Geislingen": "GLB", 
    "Geislingen an der Steige": "GLI", 
    "Gemmingen": "GMG", 
    "Gemmrigheim": "GGM", 
    "Gengenbach": "GGH", 
    "Gerabronn": "GBN", 
    "Gerabronn (B\u00fchlerzell)": "GAZ", 
    "Geradstetten": "79X", 
    "Gerlachsheim": "GWB", 
    "Gerlingen": "GLG", 
    "Gernsbach": "GBH", 
    "Gerstetten": "GE5", 
    "Giengen": "GGN", 
    "Gingen an der Fils": "GGF", 
    "Glatten": "GLN", 
    "Gomaringen": "GOM", 
    "Gondelsheim": "78I", 
    "Gosheim": "GOI", 
    "Gottenheim": "NOO", 
    "Gottmadingen": "GOT", 
    "Graben-Neudorf": "GRN", 
    "Grafenberg": "GFB", 
    "Grafenhausen": "GFH", 
    "Grauelsbaum": "RLB", 
    "Greffern/Rheinm\u00fcnster": "78T", 
    "Grenzach-Wyhlen": "GWY", 
    "Griesheim (Offenburg)": "GMO", 
    "Griesingen": "GWG", 
    "Grossbettlingen": "GOB", 
    "Grossbottwar": "GBW", 
    "Grosseichholzheim": "HHO", 
    "Grossheppach": "79Y", 
    "Grossingersheim": "79Q", 
    "Grossrinderfeld": "GZD", 
    "Gruibingen": "GBE", 
    "Gr\u00fcnberg (Jagstzell)": "GGJ", 
    "Gr\u00fcnkraut": "GKT", 
    "Gr\u00fcnsfeld": "GUU", 
    "Gschwend": "GWD", 
    "Gundelfingen": "GFI", 
    "Gundelfingen (M\u00fcnsingen)": "GDM", 
    "Gundelsheim": "GUN", 
    "Gussenstadt": "GUS", 
    "Gutach (Schwarzwaldbahn)": "GAH", 
    "Gutach im Breisgau": "GUC", 
    "G\u00e4rtringen": "GTN", 
    "G\u00e4ufelden": "AEU", 
    "G\u00f6ggingen": "5GG", 
    "G\u00f6ppingen": "GON", 
    "G\u00f6rwihl": "GWL", 
    "G\u00fcglingen": "GGI", 
    "G\u00fcnterstal": "GUQ", 
    "G\u00fctenbach": "GZH", 
    "Haeusern": "HUU", 
    "Hagnau": "HZU", 
    "Haigerloch": "RUW", 
    "Hailtingen": "HL2", 
    "Haiterbach": "HAH", 
    "Hambr\u00fccken": "BWV", 
    "Hardheim": "HDH", 
    "Hardt": "77T", 
    "Hardt bei N\u00fcrtingen": "HNT", 
    "Hardthausen am Kocher": "HHK", 
    "Hartheim": "HMT", 
    "Haslach im Kinzigtal": "HLC", 
    "Hassmersheim": "HXX", 
    "Hattenhofen": "HNO", 
    "Hauenstein": "HUT", 
    "Hausach": "HSH", 
    "Hausen": "77L", 
    "Hayingen": "HYN", 
    "Hechingen": "HEC", 
    "Heddesheim": "HDM", 
    "Hedelfingen": "HPF", 
    "Heidelberg": "HEI", 
    "Heidenheim": "HEM", 
    "Heidenheim an der Brenz": "HD2", 
    "Heilbronn": "HEN", 
    "Heiligenberg": "HEY", 
    "Heiligkreuzsteinach": "49H", 
    "Heiligkreuztal": "HTX", 
    "Heimerdingen": "HMN", 
    "Heimsheim": "HIM", 
    "Heiningen": "HNE", 
    "Heiterbach": "HIT", 
    "Heitersheim": "HTH", 
    "Helmlingen": "HML", 
    "Helmstadt-Bargen": "HXN", 
    "Hemmingen": "MIG", 
    "Hemsbach": "HBW", 
    "Herbertingen": "XRT", 
    "Herbolzheim": "HBM", 
    "Herbrechtingen": "HER", 
    "Herdwangen": "HHR", 
    "Hermaringen": "HMG", 
    "Heroldstatt": "HET", 
    "Herrenberg": "HNG", 
    "Hessigheim": "HGH", 
    "Hettingen": "HTQ", 
    "Heubach": "HEU", 
    "Heuchlingen": "HCG", 
    "Hildrizhausen": "HIZ", 
    "Hilzingen": "HLZ", 
    "Hinterzarten": "HZA", 
    "Hirrlingen": "HIG", 
    "Hirschberg": "HGD", 
    "Hochdorf": "5HR", 
    "Hockenheim": "HOC", 
    "Hofweier": "77S", 
    "Hohberg": "HR3", 
    "Hohenlohe": "HF4", 
    "Hohenstadt": "OSA", 
    "Hohenstein": "OHT", 
    "Hohentengen am Hochrhein": "HHE", 
    "Hohentengen bei Bad Saulgau": "HNU", 
    "Holzbronn": "HZO", 
    "Holzgerlingen": "ZLG", 
    "Honau": "HNA", 
    "Honhardt": "ODT", 
    "Horb": "HOB", 
    "Horgen": "YON", 
    "Horgenzell": "32E", 
    "Hornberg": "77P", 
    "Huttenheim": "ZHM", 
    "Huttingen": "HZZ", 
    "H\u00e4g-Ehrsberg": "HEZ", 
    "H\u00f6fen an der Enz": "HFE", 
    "H\u00f6pfingen": "HPG", 
    "H\u00fcffenhardt": "HFF", 
    "H\u00fcfingen": "UEF", 
    "H\u00fcgelsheim": "GH8", 
    "H\u00fcttisheim": "HTM", 
    "H\u00fcttlingen": "HTG", 
    "Ichenheim": "CIH", 
    "Iffezheim": "IFF", 
    "Igersheim": "IGH", 
    "Iggingen": "IGG", 
    "Ihringen": "IHR", 
    "Illerrieden": "IDN", 
    "Illingen": "ILG", 
    "Ilsfeld": "FLD", 
    "Ilshofen": "IZN", 
    "Ilvesheim": "78V", 
    "Immendingen": "77Y", 
    "Immenstaad am Bodensee": "IMD", 
    "Ingelfingen": "IGF", 
    "Ingersheim": "IGM", 
    "Inneringen": "BGJ", 
    "Inzlingen": "INZ", 
    "Iptingen": "IPT", 
    "Isny im Allg\u00e4u": "ISY", 
    "Ispringen": "ISP", 
    "Ittlingen": "ITG", 
    "Jagsthausen": "JTU", 
    "Jagstzell": "JAG", 
    "Jestetten": "JES", 
    "Kaempfelbach": "ZKH", 
    "Kandern": "KQN", 
    "Kappel-Grafenhausen": "KGH", 
    "Kappelrodeck": "KRK", 
    "Kappelwindeck": "KWP", 
    "Karlsbad": "KQD", 
    "Karlsdorf-Neuthard": "KNH", 
    "Karlsruhe": "KAE", 
    "Kehl": "KEH", 
    "Keltern": "KWN", 
    "Kenzingen": "KZI", 
    "Kerkingen": "KKG", 
    "Kernen": "KNE", 
    "Ketsch": "KTH", 
    "Kieselbronn": "KIB", 
    "Kippenheim": "KIP", 
    "Kirchardt": "KRD", 
    "Kirchberg an der Iller": "KXI", 
    "Kirchberg an der Jagst": "KGJ", 
    "Kirchberg an der Murr": "KBM", 
    "Kirchdorf (Iller)": "KDF", 
    "Kirchentellinsfurt": "ZTI", 
    "Kirchheim": "KCI", 
    "Kirchheim Unter Teck": "KHC", 
    "Kirchheim am Neckar": "KNC", 
    "Kirchheim/Teck": "KIR", 
    "Kirchhofen": "KKH", 
    "Kirchzarten": "KCH", 
    "Kisslegg": "KIS", 
    "Kleines Wiesental": "KWI", 
    "Klettgau": "KLU", 
    "Knittlingen": "78D", 
    "Kochendorf": "KHO", 
    "Kohlberg": "KHL", 
    "Kolbingen": "77X", 
    "Konstanz": "KON", 
    "Korb": "KOX", 
    "Korntal-M\u00fcnchingen": "KMG", 
    "Kornwestheim": "KOR", 
    "Kraichtal": "KIL", 
    "Krauchenwies": "KRH", 
    "Krautheim": "KRM", 
    "Kressberg": "KGZ", 
    "Kressbronn am Bodensee": "KAB", 
    "Kronau": "KOU", 
    "Kuchen": "CEN", 
    "Kupferzell": "KUZ", 
    "Kuppenheim": "KUP", 
    "Kusterdingen": "KTD", 
    "K\u00f6ngen": "KNN", 
    "K\u00f6nigheim": "KMB", 
    "K\u00f6nigsbach-Stein": "STZ", 
    "K\u00f6nigsbronn": "KSB", 
    "K\u00f6nigseggwald": "KGG", 
    "K\u00f6nigsfeld im Schwarzwald": "77V", 
    "K\u00f6nigsheim": "KHE", 
    "K\u00fclsheim": "KIM", 
    "K\u00fcnzelsau": "VMG", 
    "K\u00fcrnbach": "78M", 
    "K\u00fcssaberg": "KUA", 
    "Ladenburg": "LRG", 
    "Lahr": "LAR", 
    "Laichingen": "LCG", 
    "Langenargen": "LIV", 
    "Langenau": "LGU", 
    "Langenbach": "LGB", 
    "Langenbeutingen": "LET", 
    "Langenburg": "LBU", 
    "Langenenslingen": "LGL", 
    "Lauchheim": "LAI", 
    "Lauchringen": "LHG", 
    "Lauda-K\u00f6nigshofen": "LKN", 
    "Laudenbach": "LDC", 
    "Lauf": "LQF", 
    "Laufenburg": "LFG", 
    "Lauffen am Neckar": "LFN", 
    "Laupheim": "LPM", 
    "Lautenbach": "LQB", 
    "Lauterbach": "77U", 
    "Lauterstein": "LUR", 
    "Legelshurst": "LE7", 
    "Lehrensteinsfeld": "79N", 
    "Leibertingen": "82K", 
    "Leimen": "LMN", 
    "Leinfelden-Echterdingen": "ZQG", 
    "Leingarten": "LGT", 
    "Lenningen": "LEN", 
    "Lenzkirch": "LZK", 
    "Leonberg": "LEO", 
    "Leuchtenberg": "LE4", 
    "Leutenbach": "ZLH", 
    "Leutershausen": "LKB", 
    "Leutkirch im Allg\u00e4u": "LEU", 
    "Lichtenau (Baden)": "LCT", 
    "Lichtenstein (Reutlingen)": "LWU", 
    "Limbach": "LMB", 
    "Linkenheim": "LKH", 
    "Linkenheim-Hochstetten": "LYN", 
    "Lobbach": "LOA", 
    "Loffenau": "LF8", 
    "Lomersheim": "LO2", 
    "Lonsee": "LS3", 
    "Lorch": "LOC", 
    "Lossburg": "LOG", 
    "Lottstetten": "LTS", 
    "Ludwigsburg": "LWG", 
    "L\u00f6chgau": "LCA", 
    "L\u00f6ffingen": "LFF", 
    "L\u00f6rch": "LRH", 
    "L\u00f6rrach": "LOE", 
    "L\u00f6wenstein": "79K", 
    "Magstadt": "MAS", 
    "Mahlberg": "MAB", 
    "Mainhardt": "MNT", 
    "Malmsheim": "ML5", 
    "Malsburg": "MLU", 
    "Malsch": "MLH", 
    "Malterdingen": "MDN", 
    "Mannheim": "MHG", 
    "Marbach am Neckar": "MNC", 
    "Markdorf": "MAF", 
    "Markgr\u00f6ningen": "MKG", 
    "Marlen": "MRL", 
    "Marzell": "MZL", 
    "Maselheim": "ME3", 
    "Massenbachhausen": "79O", 
    "Mauer": "MUX", 
    "Maulbronn": "MBN", 
    "Maulburg": "MLB", 
    "Maxau": "MXA", 
    "Meckenbeuren": "MBR", 
    "Meckesheim": "CKE", 
    "Meersburg": "MBG", 
    "Mehrstetten": "ZBS", 
    "Meissenheim": "5ME", 
    "Melchingen": "MC3", 
    "Mengen": "MGE", 
    "Menzingen": "78K", 
    "Merdingen": "MTE", 
    "Merklingen": "MEJ", 
    "Merzhausen": "ZHU", 
    "Messkirch": "MES", 
    "Messstetten": "TEN", 
    "Metzingen": "MTN", 
    "Michelbach am Heuchelberg": "Z4Z", 
    "Mietingen": "MGI", 
    "Mittelbiberach": "82D", 
    "Mochenwangen": "MWN", 
    "Monchweiler": "MWW", 
    "Moos": "77J", 
    "Moosburg bei Bad Buchau": "MOC", 
    "Mosbach": "MOB", 
    "Mudau": "MUU", 
    "Muggensturm": "MGS", 
    "Mulfingen": "MFI", 
    "Mundelsheim": "79P", 
    "Munderkingen": "MDK", 
    "Murg": "MRG", 
    "Murr": "MRW", 
    "Murrhardt": "MHT", 
    "Mutlangen": "MXL", 
    "M\u00f6ckm\u00fchl": "MML", 
    "M\u00f6gglingen": "MGW", 
    "M\u00f6glingen": "MLN", 
    "M\u00f6nsheim": "MOM", 
    "M\u00f6ssingen": "MOI", 
    "M\u00f6tzingen": "TZI", 
    "M\u00fchlacker": "MUL", 
    "M\u00fchlenberg": "MLG", 
    "M\u00fchlhausen": "78X", 
    "M\u00fchlhausen im T\u00e4le": "MYH", 
    "M\u00fchlhausen-Ehingen": "MHU", 
    "M\u00fcllheim": "MUE", 
    "M\u00fcnsingen": "MGN", 
    "M\u00fcnzesheim": "78L", 
    "Nagold": "NAG", 
    "Nattheim": "NAT", 
    "Neckarau": "NKU", 
    "Neckarbischofsheim": "NKB", 
    "Neckarelz": "NEZ", 
    "Neckargem\u00fcnd": "NMD", 
    "Neckargerach": "78R", 
    "Neckarsulm": "NEM", 
    "Neckartailfingen": "NTA", 
    "Neckartenzlingen": "NKZ", 
    "Neckarwestheim": "NKW", 
    "Neckarzimmern": "NZE", 
    "Neenstetten": "NNE", 
    "Nehren": "NEY", 
    "Neidenstein": "NDN", 
    "Nellingen": "NGN", 
    "Nenningen": "79F", 
    "Neresheim": "NSH", 
    "Neu-Kupfer": "FER", 
    "Neubulach": "NBL", 
    "Neudenau": "NDA", 
    "Neuenburg am Rhein": "NBR", 
    "Neuenb\u00fcrg": "NEG", 
    "Neuenstadt am Kocher": "NNT", 
    "Neuenstein": "NTE", 
    "Neuffen": "NXF", 
    "Neufra": "NFA", 
    "Neuhausen": "NUX", 
    "Neuhausen auf den Fildern": "NHF", 
    "Neuh\u00fctten": "NUZ", 
    "Neukirch": "82F", 
    "Neuler": "N2R", 
    "Neulussheim": "NLM", 
    "Neumalsch": "NL3", 
    "Neuried/Baden": "NE3", 
    "Neuweier": "NRW", 
    "Neuweiler": "NWR", 
    "Niebelsbach": "BWJ", 
    "Niedereschach": "NDC", 
    "Niedernhall": "BNI", 
    "Niederrotweil": "EED", 
    "Niederstetten": "BWT", 
    "Niederstotzingen": "NSG", 
    "Niefern": "NFN", 
    "Nimburg": "IM7", 
    "Nordheim": "NHE", 
    "Nordrach": "NRC", 
    "Notzingen": "NZN", 
    "Nufringen": "NUF", 
    "Nusplingen": "PJQ", 
    "Nussdorf": "NZF", 
    "Nussloch": "NUH", 
    "N\u00fcrtingen": "NUN", 
    "Oberbergen": "FR9", 
    "Oberberken": "OBZ", 
    "Oberboihingen": "ONN", 
    "Oberderdingen": "ODN", 
    "Oberdischingen": "ODC", 
    "Oberharmersbach": "OBQ", 
    "Oberhausen-Rheinhausen": "ORN", 
    "Oberjettingen": "79D", 
    "Oberkirch": "OKH", 
    "Oberkochen": "OKO", 
    "Oberndorf am Neckar": "ODF", 
    "Obernheim": "OHK", 
    "Oberopfingen": "OPF", 
    "Oberreute": "77F", 
    "Oberriexingen": "OXG", 
    "Oberrot": "OOT", 
    "Oberrotweil (Vogtsburg/Kaiserstuhl)": "VO2", 
    "Obersontheim": "OZH", 
    "Oberstenfeld": "OFD", 
    "Oberstetten": "XHH", 
    "Obersulm": "OSM", 
    "Oberteuringen": "OEU", 
    "Oberuhldingen": "82E", 
    "Oberwolfach": "OBH", 
    "Obrigheim": "OGH", 
    "Ochsenhausen": "OCH", 
    "Odenwald": "ODZ", 
    "Oedheim": "OEM", 
    "Offenau": "ONA", 
    "Offenburg": "OFG", 
    "Ofterdingen": "ODG", 
    "Oftersheim": "OFM", 
    "Ohlsbach": "77O", 
    "Ohmden": "6MN", 
    "Oppelsbohm": "79V", 
    "Oppenau": "OPU", 
    "Oppenweiler": "OPE", 
    "Orsingen-Nenzingen": "OGZ", 
    "Ortenberg": "ONR", 
    "Ostelsheim": "OIM", 
    "Osterburken": "OST", 
    "Ostfildern": "OSF", 
    "Ostrach": "OTH", 
    "Ottenbach": "ZDJ", 
    "Ottenheim": "OHI", 
    "Ottenh\u00f6fen im Schwarzwald": "77Q", 
    "Ottersweier": "OTW", 
    "Owen": "OWN", 
    "Owingen": "OWG", 
    "Pfaffenhofen": "PNH", 
    "Pfaffenweiler": "VAT", 
    "Pfalzgrafenweiler": "PGR", 
    "Pfedelbach": "PFL", 
    "Pfedlbach": "PFZ", 
    "Pfinztal": "PZA", 
    "Pforzheim": "PFO", 
    "Pfullendorf": "PFU", 
    "Pfullingen": "PFN", 
    "Philippsburg": "PHG", 
    "Plankstadt": "PKS", 
    "Plattenhardt": "PDT", 
    "Pleidelsheim": "PLH", 
    "Pliezhausen": "PLS", 
    "Plochingen": "PLO", 
    "Pl\u00fcderhausen": "PHN", 
    "Radolfzell": "RAD", 
    "Rammingen": "RMM", 
    "Rangendingen": "DXG", 
    "Rastatt": "RAS", 
    "Rauenberg": "78Y", 
    "Ravensburg": "RAV", 
    "Rechberghausen": "79G", 
    "Reichartshausen": "RTJ", 
    "Reichenau": "RNU", 
    "Reichenbach": "78Q", 
    "Reichenbach am Heuberg": "REX", 
    "Reichenbach an der Fils": "RFI", 
    "Reilingen": "RII", 
    "Reinau": "RNX", 
    "Reisenbach": "RIB", 
    "Remchingen": "EMC", 
    "Remseck am Neckar": "RNK", 
    "Remshalden": "RHN", 
    "Renchen": "RCN", 
    "Renningen": "RNN", 
    "Reutlingen": "REU", 
    "Rheinau, Ortenaukreis": "RHI", 
    "Rheinfelden": "RFN", 
    "Rheinhausen": "RNH", 
    "Rheinm\u00fcnster": "RHR", 
    "Rheinstetten": "SHT", 
    "Rickenbach": "RKB", 
    "Riederich": "RDZ", 
    "Riedlingen": "RIE", 
    "Riegel": "77G", 
    "Rielasingen-Worblingen": "RIA", 
    "Riesb\u00fcrg": "RBW", 
    "Rietheim-Weilheim": "RWM", 
    "Ringsheim": "RGI", 
    "Rohrdorf (Schwarzwald)": "RRC", 
    "Roigheim": "RGH", 
    "Rosenberg (Baden)": "RRB", 
    "Rosenberg/Ostalb": "RSG", 
    "Rosenfeld": "RSD", 
    "Rosengarten": "JRG", 
    "Rot an der Rot": "RDT", 
    "Rottenacker": "RTA", 
    "Rottenburg": "RTO", 
    "Rottenburg am Neckar": "ZFI", 
    "Rottweil": "ROL", 
    "Rudersberg": "RUD", 
    "Ruppertshofen, Ostalbkreis": "RPP", 
    "Russheim": "78J", 
    "Rust": "RXT", 
    "Rutesheim": "RTM", 
    "R\u00f6merstein": "5RN", 
    "R\u00fcmmingen": "RM9", 
    "Sachsenheim": "SSN", 
    "Sailach": "SLA", 
    "Salach": "SLX", 
    "Salem": "KVV", 
    "Salzstetten": "78G", 
    "Sandhausen": "SAN", 
    "Sankt Blasien": "SBL", 
    "Sankt Georgen im Schwarzwald": "SGS", 
    "Sankt Johann": "SJO", 
    "Sankt Johann (Reutlingen)": "TTS", 
    "Sankt Leon-Rot": "SNL", 
    "Sankt M\u00e4rgen": "77D", 
    "Sankt Peter": "NPR", 
    "Sasbach": "SAB", 
    "Sasbach am Kaiserstuhl": "SMK", 
    "Sasbachwalden": "77M", 
    "Satteldorf": "2SD", 
    "Sauldorf": "SDC", 
    "Saulgau": "SLU", 
    "Schallstadt": "SSX", 
    "Schapbach": "SGY", 
    "Scharenstetten": "ARR", 
    "Scharnhausen": "HUK", 
    "Schechingen": "S3B", 
    "Scheer": "SEQ", 
    "Schefflenz": "ZFW", 
    "Schelklingen": "SCI", 
    "Schemmerberg": "SMM", 
    "Schemmerhofen": "SMH", 
    "Schenkenzell": "SZL", 
    "Schiltach": "SIC", 
    "Schlat": "SHC", 
    "Schliengen": "SLI", 
    "Schlier": "CHR", 
    "Schlierbach": "SLR", 
    "Schloss": "SA4", 
    "Schluchsee": "SUC", 
    "Schmiechen": "XMN", 
    "Schonach": "SCC", 
    "Schopfheim": "SHM", 
    "Schopfloch/Freudenstadt": "SLH", 
    "Schorndorf": "SDF", 
    "Schozach": "SZ8", 
    "Schramberg": "SCG", 
    "Schriesheim": "SCM", 
    "Schrozberg": "ZFR", 
    "Schuttertal": "UTT", 
    "Schutterwald": "SRW", 
    "Schwaigern": "SWF", 
    "Schwaikheim": "SWK", 
    "Schwanau": "SWJ", 
    "Schwanheim": "CHW", 
    "Schwarzach": "SZH", 
    "Schwarzenbach": "SCP", 
    "Schwendi": "CWD", 
    "Schwenningen": "SWV", 
    "Schwetzingen": "SCH", 
    "Schwieberdingen": "SWI", 
    "Schw\u00e4bisch Gm\u00fcnd": "SGD", 
    "Schw\u00e4bisch Hall": "SHL", 
    "Schw\u00f6rstadt": "77K", 
    "Sch\u00f6mberg": "SCQ", 
    "Sch\u00f6mberg (Calw)": "SBE", 
    "Sch\u00f6naich": "SNJ", 
    "Sch\u00f6nau": "78Z", 
    "Sch\u00f6nau im Schwarzwald": "SMS", 
    "Sch\u00f6nbrunn/Baden": "CNN", 
    "Sch\u00f6ntal": "SAJ", 
    "Sch\u00f6nwald": "77W", 
    "Seckach": "SKC", 
    "Seebach": "SBQ", 
    "Seebronn": "EEO", 
    "Seelbach": "SXE", 
    "Sennfeld": "ZFX", 
    "Sersheim": "SXM", 
    "Sexau": "SEU", 
    "Siegelsbach": "SGL", 
    "Sigmaringen": "SMG", 
    "Sigmaringendorf": "XIG", 
    "Simmersfeld": "SM3", 
    "Simmozheim": "SZM", 
    "Simonswald": "SSW", 
    "Sindelfingen": "SDN", 
    "Singen": "SIN", 
    "Sinsheim": "SIH", 
    "Sinzheim": "SZZ", 
    "Solden": "2SO", 
    "Sonnenb\u00fchl": "ONL", 
    "Sontheim an der Brenz": "SNM", 
    "Spaichingen": "SPA", 
    "Spiegelberg": "ZDQ", 
    "Spraitbach": "SIP", 
    "Sp\u00f6ck": "78O", 
    "Stadt Kehl": "2SK", 
    "Staufen im Breisgau": "SBR", 
    "Steinach (Ortenaukreis)": "SNO", 
    "Steinen": "SEI", 
    "Steinenbronn": "SBO", 
    "Steinfurt": "STT", 
    "Steinheim am Albuch": "79H", 
    "Steinheim am der Murr": "79R", 
    "Steinmauern": "SIU", 
    "Steinweiler": "STW", 
    "Stetten": "ZHB", 
    "Stetten am Kalten Markt": "ST2", 
    "Stimpfach": "SMP", 
    "Stockach": "SKH", 
    "Stollhofen": "SOC", 
    "Strassberg": "82L", 
    "Straubenhardt": "SHR", 
    "Stutensee": "SSE", 
    "Stuttgart": "STR", 
    "St\u00fchlingen": "SHG", 
    "Sulz am Neckar": "SMC", 
    "Sulzbach an der Murr": "SQR", 
    "Sulzbach-Laufen": "SLZ", 
    "Sulzburg": "77A", 
    "Sulzdorf": "S8L", 
    "Sulzfeld": "UZD", 
    "S\u00f6hnstetten": "SXT", 
    "S\u00fcssen": "SUS", 
    "Talheim": "TLH", 
    "Tamm": "TAM", 
    "Tannhausen": "79T", 
    "Tannheim": "TAH", 
    "Tauberbischofsheim": "TAU", 
    "Tengen": "TNN", 
    "Teningen": "TGN", 
    "Tennenbronn": "ZHP", 
    "Tettnang": "TET", 
    "Tiefenbronn": "TWN", 
    "Tieringen": "B6T", 
    "Titisee-Neustadt": "TNE", 
    "Todtmoos": "TMO", 
    "Todtnau": "TOD", 
    "Triberg": "TRG", 
    "Trochtelfingen": "TRF", 
    "Trochtelfingen (Bopfingen)": "TRC", 
    "Trossingen": "TRN", 
    "Tumlingen": "78H", 
    "Tuningen": "TUN", 
    "Tuttlingen": "TUT", 
    "T\u00fcbingen": "TUE", 
    "Ubstadt": "78P", 
    "Ubstadt-Weiher": "UBW", 
    "Uhingen": "UHI", 
    "Ulm": "ULM", 
    "Umkirch": "UKH", 
    "Ummendorf": "UMM", 
    "Undingen (Sonnenb\u00fchl)": "36S", 
    "Untereisesheim": "79J", 
    "Unterensingen": "URG", 
    "Untergroningen": "UGO", 
    "Untergruppenbach": "UPP", 
    "Unterkirchberg": "82C", 
    "Unterkirnach": "UNE", 
    "Unterkochen": "UNK", 
    "Untermarchtal": "ZID", 
    "Unterm\u00fcnkheim": "UMH", 
    "Unteropfingen": "UPF", 
    "Unterreichenbach": "UBH", 
    "Unterschefflenz": "78S", 
    "Unterschneidheim": "USH", 
    "Unterturkheim": "UN7", 
    "Unterweissach": "79U", 
    "Urbach": "URB", 
    "Urberg": "URQ", 
    "Uttenweiler": "UTW", 
    "Utzenfeld": "UZF", 
    "Vaihingen an der Enz": "VAI", 
    "Vellberg": "VLB", 
    "Villingen-Schwenningen": "VIS", 
    "Villingendorf": "VLG", 
    "Vogt": "82I", 
    "Vogtsburg im Kaiserstuhl": "VOG", 
    "Volkertshausen": "VKH", 
    "V\u00f6hrenbach": "VRB", 
    "V\u00f6hringen": "VHR", 
    "V\u00f6rstetten": "77E", 
    "Wagh\u00e4usel": "WGL", 
    "Waiblingen": "WAI", 
    "Waibstadt": "WBD", 
    "Wain": "WYI", 
    "Waldachtal": "WTL", 
    "Waldbronn": "WBO", 
    "Waldbrunn": "ZIQ", 
    "Waldburg": "WUW", 
    "Walddorf": "AOF", 
    "Walddorfh\u00e4slach": "DWO", 
    "Waldenbuch": "WBH", 
    "Waldenburg": "WBW", 
    "Waldkirch": "WKR", 
    "Waldshut-Tiengen": "WAT", 
    "Waldstetten": "WXT", 
    "Walheim": "WLE", 
    "Walldorf": "WDF", 
    "Walld\u00fcrn": "WRN", 
    "Wallhausen": "WHW", 
    "Walzbachtal": "WZT", 
    "Wangen": "WG5", 
    "Wangen im Allg\u00e4u": "WGN", 
    "Wannweil": "ZAM", 
    "Wehingen": "WGQ", 
    "Wehr": "WQR", 
    "Weidenstetten": "WYS", 
    "Weikersheim": "WKK", 
    "Weil": "WLK", 
    "Weil (Tengen)": "WIV", 
    "Weil am Rhein": "WLR", 
    "Weil der Stadt": "WDS", 
    "Weil im Dorf": "WYD", 
    "Weil im Sch\u00f6nbuch": "WSH", 
    "Weilheim an der Teck": "WLH", 
    "Weingarten": "WGA", 
    "Weinheim": "WHM", 
    "Weinsberg": "WSB", 
    "Weinstadt": "ADT", 
    "Weisenbach": "WEH", 
    "Weissach": "WSC", 
    "Weissbach (Hohenlohe)": "WSQ", 
    "Weisweil": "WWL", 
    "Wellendingen": "WDI", 
    "Welschingen": "WGW", 
    "Welzheim": "WZM", 
    "Wembach": "WBC", 
    "Wendlingen am Neckar": "WNN", 
    "Werbach": "WCC", 
    "Wernau": "WRU", 
    "Wertheim": "WTM", 
    "Westerheim": "WSM", 
    "Westhausen": "WWE", 
    "Westheim": "82A", 
    "Wettingen": "WTI", 
    "Wieden": "ZJC", 
    "Wiernsheim": "WRM", 
    "Wiesenbach": "78W", 
    "Wiesensteig": "WNA", 
    "Wiesloch": "WSY", 
    "Wildberg": "WDB", 
    "Wilfingen": "WJF", 
    "Wilhelmsdorf": "82J", 
    "Wilhelmsfeld": "79A", 
    "Willsbach": "79L", 
    "Willst\u00e4tt": "WST", 
    "Wimsheim": "WBM", 
    "Winden Im Elztal": "WXE", 
    "Windischbuch": "WH3", 
    "Winnenden": "WIX", 
    "Winterbach": "WTC", 
    "Winterlingen": "82M", 
    "Wittenschwand": "WJT", 
    "Wittlingen": "WYG", 
    "Wittnau": "ITA", 
    "Wolfach": "WDL", 
    "Wolfegg": "WFE", 
    "Wolfenweiler": "ST8", 
    "Wolfschlugen": "WOU", 
    "Wolpadingen": "WOP", 
    "Wolpertshausen": "QWP", 
    "Wolpertswende": "WPW", 
    "Wolterdingen": "BQG", 
    "Wurmberg": "WMG", 
    "Wurmlingen": "ZJF", 
    "Wutoeschingen": "ZJL", 
    "Wyhl": "77H", 
    "W\u00e4schenbeuren": "WCB", 
    "W\u00f6rt": "WOT", 
    "W\u00fcrtingen": "WU2", 
    "W\u00fcstenrot": "WUT", 
    "Zaberfeld": "ZAB", 
    "Zaisenhausen": "ZIZ", 
    "Zell (B\u00f6rtlingen)": "ZLS", 
    "Zell (Esslingen am Neckar)": "LLK", 
    "Zell (Oppenweiler)": "LLO", 
    "Zell (Riedlingen)": "ZRI", 
    "Zell (Schrozberg)": "ZLZ", 
    "Zell am Harmersbach": "ZEH", 
    "Zell im Wiesental": "ZEW", 
    "Zell unter Aichelberg": "ZAG", 
    "Zimmern ob Rottweil": "ZMR", 
    "Zuzenhausen": "ZZH", 
    "Zwiefalten": "AWI", 
    "jungingen": "JUL", 
    "\u00c4pfingen": "AFI", 
    "\u00d6hningen": "OHG", 
    "\u00d6hringen": "OEH", 
    "\u00d6lbronn-D\u00fcrrn": "NNR", 
    "\u00d6stringen": "OES", 
    "\u00d6tigheim": "OTG", 
    "\u00d6tisheim": "OEI", 
    "\u00dcberlingen": "UEB", 
    "\u00dchlingen": "ULI"
}