{
    "Agathonisi": "AGN", 
    "Agia Marina Lerou": "AML", 
    "Arkioi Dodekanissou": "ARD", 
    "Astyp\u00e1laia": "JTY", 
    "Avlona": "GAE", 
    "Diaf\u00e1nion": "DIA", 
    "Farmakonissi Dodekanissos": "FAM", 
    "Halki Dodekanison": "HAL", 
    "Kalathos Rodou": "KLD", 
    "Kardamaina Kos": "KRM", 
    "Kastellorizou (ex Meg\u00edsti)": "KAS", 
    "K\u00e1lymnos": "KMI", 
    "Lindos Rodou": "LDR", 
    "Lipso\u00ed": "LIP", 
    "Mastichari Kos": "MXK", 
    "Phserimos Dodekanisou": "PSE", 
    "Tilos": "TIL"
}