{
    "Abrunheira": "ABR", 
    "Alagoa": "ALG", 
    "Algoz": "AL8", 
    "Arazede": "AZD", 
    "Arganil": "AGN", 
    "Arrifana": "ARF", 
    "Cantanhede": "CTH", 
    "Cernache": "CER", 
    "Coimbra": "CBP", 
    "Coimbra CDP": "CDC", 
    "Coja": "COJ", 
    "Condeixa a Nova": "CAN", 
    "Covelo": "CVO", 
    "Figueira da Foz": "FDF", 
    "Foz de Arouce": "FDR", 
    "G\u00f3is": "GOI", 
    "Leirosa": "TZJ", 
    "Lous\u00e3": "LSA", 
    "Mira": "MIR", 
    "Miranda do Corvo": "MCV", 
    "Montemor-o-Velho": "MMV", 
    "Moura": "MOC", 
    "Murtede": "MTE", 
    "Nogueira do Cravo": "NDC", 
    "Oliveira do Hospital": "OHP", 
    "Pampilhosa da Serra": "PPS", 
    "Penacova": "PCV", 
    "Penela": "PNL", 
    "Rebordosa": "REB", 
    "Senhora das Febres": "SDF", 
    "Soure": "SOU", 
    "Souselas": "ELA", 
    "Souzelas": "SZL", 
    "S\u00e3o Gi\u00e3o": "IAO", 
    "S\u00e3o Paio de Grama\u00e7os": "SPG", 
    "T\u00e1bua": "TAB", 
    "Vila Nova de Poiares": "VNP", 
    "Vila Pouca da Beira": "VPB"
}